{
  "id": [
    "33805830"
  ],
  "source": [
    "MED"
  ],
  "pmid": [
    "33805830"
  ],
  "pmcid": [
    "PMC8000418"
  ],
  "fullTextIdList": [
    {
      "fullTextId": [
        "PMC8000418"
      ]
    }
  ],
  "doi": [
    "10.3390/pharmaceutics13030387"
  ],
  "title": [
    "Excipients in the Paediatric Population: A Review."
  ],
  "authorString": [
    "Rouaz K, Chiclana-Rodríguez B, Nardi-Ricart A, Suñé-Pou M, Mercadé-Frutos D, Suñé-Negre JM, Pérez-Lozano P, García-Montoya E."
  ],
  "authorList": [
    {
      "author": [
        {
          "fullName": [
            "Rouaz K"
          ],
          "firstName": [
            "Khadija"
          ],
          "lastName": [
            "Rouaz"
          ],
          "initials": [
            "K"
          ],
          "authorId": [
            {
              "_": "0000-0002-7819-2773",
              "$": {
                "type": "ORCID"
              }
            }
          ],
          "authorAffiliationDetailsList": [
            {
              "authorAffiliation": [
                {
                  "affiliation": [
                    "Department of Pharmacy and Pharmaceutical Technology and Physical Chemistry, Faculty of Pharmacy and Food Sciences, University of Barcelona, Av. Joan XXIII, 27-31, 08028 Barcelona, Spain."
                  ]
                }
              ]
            }
          ]
        },
        {
          "fullName": [
            "Chiclana-Rodríguez B"
          ],
          "firstName": [
            "Blanca"
          ],
          "lastName": [
            "Chiclana-Rodríguez"
          ],
          "initials": [
            "B"
          ],
          "authorId": [
            {
              "_": "0000-0002-9279-536X",
              "$": {
                "type": "ORCID"
              }
            }
          ],
          "authorAffiliationDetailsList": [
            {
              "authorAffiliation": [
                {
                  "affiliation": [
                    "Department of Pharmacy and Pharmaceutical Technology and Physical Chemistry, Faculty of Pharmacy and Food Sciences, University of Barcelona, Av. Joan XXIII, 27-31, 08028 Barcelona, Spain."
                  ]
                }
              ]
            }
          ]
        },
        {
          "fullName": [
            "Nardi-Ricart A"
          ],
          "firstName": [
            "Anna"
          ],
          "lastName": [
            "Nardi-Ricart"
          ],
          "initials": [
            "A"
          ],
          "authorId": [
            {
              "_": "0000-0001-9548-3903",
              "$": {
                "type": "ORCID"
              }
            }
          ],
          "authorAffiliationDetailsList": [
            {
              "authorAffiliation": [
                {
                  "affiliation": [
                    "Department of Pharmacy and Pharmaceutical Technology and Physical Chemistry, Faculty of Pharmacy and Food Sciences, University of Barcelona, Av. Joan XXIII, 27-31, 08028 Barcelona, Spain."
                  ]
                }
              ]
            }
          ]
        },
        {
          "fullName": [
            "Suñé-Pou M"
          ],
          "firstName": [
            "Marc"
          ],
          "lastName": [
            "Suñé-Pou"
          ],
          "initials": [
            "M"
          ],
          "authorAffiliationDetailsList": [
            {
              "authorAffiliation": [
                {
                  "affiliation": [
                    "Department of Pharmacy and Pharmaceutical Technology and Physical Chemistry, Faculty of Pharmacy and Food Sciences, University of Barcelona, Av. Joan XXIII, 27-31, 08028 Barcelona, Spain."
                  ]
                },
                {
                  "affiliation": [
                    "Pharmacotherapy, Pharmacogenetics and Pharmaceutical Technology Research Group Bellvitge Biomedical Research Institute (IDIBELL), Av. Gran via de l'Hospitalet, 199-203, 08090 Barcelona, Spain."
                  ]
                }
              ]
            }
          ]
        },
        {
          "fullName": [
            "Mercadé-Frutos D"
          ],
          "firstName": [
            "Dèbora"
          ],
          "lastName": [
            "Mercadé-Frutos"
          ],
          "initials": [
            "D"
          ],
          "authorAffiliationDetailsList": [
            {
              "authorAffiliation": [
                {
                  "affiliation": [
                    "Department of Pharmacy and Pharmaceutical Technology and Physical Chemistry, Faculty of Pharmacy and Food Sciences, University of Barcelona, Av. Joan XXIII, 27-31, 08028 Barcelona, Spain."
                  ]
                }
              ]
            }
          ]
        },
        {
          "fullName": [
            "Suñé-Negre JM"
          ],
          "firstName": [
            "Josep María"
          ],
          "lastName": [
            "Suñé-Negre"
          ],
          "initials": [
            "JM"
          ],
          "authorAffiliationDetailsList": [
            {
              "authorAffiliation": [
                {
                  "affiliation": [
                    "Department of Pharmacy and Pharmaceutical Technology and Physical Chemistry, Faculty of Pharmacy and Food Sciences, University of Barcelona, Av. Joan XXIII, 27-31, 08028 Barcelona, Spain."
                  ]
                },
                {
                  "affiliation": [
                    "Pharmacotherapy, Pharmacogenetics and Pharmaceutical Technology Research Group Bellvitge Biomedical Research Institute (IDIBELL), Av. Gran via de l'Hospitalet, 199-203, 08090 Barcelona, Spain."
                  ]
                }
              ]
            }
          ]
        },
        {
          "fullName": [
            "Pérez-Lozano P"
          ],
          "firstName": [
            "Pilar"
          ],
          "lastName": [
            "Pérez-Lozano"
          ],
          "initials": [
            "P"
          ],
          "authorId": [
            {
              "_": "0000-0001-6899-066X",
              "$": {
                "type": "ORCID"
              }
            }
          ],
          "authorAffiliationDetailsList": [
            {
              "authorAffiliation": [
                {
                  "affiliation": [
                    "Department of Pharmacy and Pharmaceutical Technology and Physical Chemistry, Faculty of Pharmacy and Food Sciences, University of Barcelona, Av. Joan XXIII, 27-31, 08028 Barcelona, Spain."
                  ]
                },
                {
                  "affiliation": [
                    "Pharmacotherapy, Pharmacogenetics and Pharmaceutical Technology Research Group Bellvitge Biomedical Research Institute (IDIBELL), Av. Gran via de l'Hospitalet, 199-203, 08090 Barcelona, Spain."
                  ]
                }
              ]
            }
          ]
        },
        {
          "fullName": [
            "García-Montoya E"
          ],
          "firstName": [
            "Encarna"
          ],
          "lastName": [
            "García-Montoya"
          ],
          "initials": [
            "E"
          ],
          "authorId": [
            {
              "_": "0000-0003-1576-5586",
              "$": {
                "type": "ORCID"
              }
            }
          ],
          "authorAffiliationDetailsList": [
            {
              "authorAffiliation": [
                {
                  "affiliation": [
                    "Department of Pharmacy and Pharmaceutical Technology and Physical Chemistry, Faculty of Pharmacy and Food Sciences, University of Barcelona, Av. Joan XXIII, 27-31, 08028 Barcelona, Spain."
                  ]
                },
                {
                  "affiliation": [
                    "Pharmacotherapy, Pharmacogenetics and Pharmaceutical Technology Research Group Bellvitge Biomedical Research Institute (IDIBELL), Av. Gran via de l'Hospitalet, 199-203, 08090 Barcelona, Spain."
                  ]
                }
              ]
            }
          ]
        }
      ]
    }
  ],
  "authorIdList": [
    {
      "authorId": [
        {
          "_": "0000-0001-6899-066X",
          "$": {
            "type": "ORCID"
          }
        },
        {
          "_": "0000-0001-9548-3903",
          "$": {
            "type": "ORCID"
          }
        },
        {
          "_": "0000-0002-7819-2773",
          "$": {
            "type": "ORCID"
          }
        },
        {
          "_": "0000-0002-9279-536X",
          "$": {
            "type": "ORCID"
          }
        },
        {
          "_": "0000-0003-1576-5586",
          "$": {
            "type": "ORCID"
          }
        }
      ]
    }
  ],
  "dataLinksTagsList": [
    {
      "dataLinkstag": [
        "altmetrics"
      ]
    }
  ],
  "journalInfo": [
    {
      "issue": [
        "3"
      ],
      "volume": [
        "13"
      ],
      "journalIssueId": [
        "3140463"
      ],
      "dateOfPublication": [
        "2021 Mar"
      ],
      "monthOfPublication": [
        "3"
      ],
      "yearOfPublication": [
        "2021"
      ],
      "printPublicationDate": [
        "2021-03-01"
      ],
      "journal": [
        {
          "title": [
            "Pharmaceutics"
          ],
          "ISOAbbreviation": [
            "Pharmaceutics"
          ],
          "medlineAbbreviation": [
            "Pharmaceutics"
          ],
          "NLMid": [
            "101534003"
          ],
          "ISSN": [
            "1999-4923"
          ],
          "ESSN": [
            "1999-4923"
          ]
        }
      ]
    }
  ],
  "pubYear": [
    "2021"
  ],
  "abstractText": [
    "This theoretical study seeks to critically review the use of excipients in the paediatric population. This study is based on the rules and recommendations of European and American drug regulatory agencies. On the one hand, this review describes the most frequent excipients used in paediatric medicine formulations, identifying the compounds that scientific literature has marked as potentially harmful regarding the side effects generated after exposure. On the other hand, this review also highlights the importance of carrying out safety -checks on the excipients, which, in most cases, are linked to toxicity studies. An excipient in the compilation of paediatric population databases is expected to target safety and toxicity, as in the STEP database. Finally, a promising pharmaceutical form for child population, ODT (Orally Disintegrating Tablets), will be studied."
  ],
  "affiliation": [
    "Department of Pharmacy and Pharmaceutical Technology and Physical Chemistry, Faculty of Pharmacy and Food Sciences, University of Barcelona, Av. Joan XXIII, 27-31, 08028 Barcelona, Spain."
  ],
  "publicationStatus": [
    "epublish"
  ],
  "language": [
    "eng"
  ],
  "pubModel": [
    "Electronic"
  ],
  "pubTypeList": [
    {
      "pubType": [
        "review-article",
        "Review",
        "Journal Article"
      ]
    }
  ],
  "keywordList": [
    {
      "keyword": [
        "Security",
        "Excipients",
        "toxicology",
        "Paediatrics",
        "Step And Odt"
      ]
    }
  ],
  "fullTextUrlList": [
    {
      "fullTextUrl": [
        {
          "availability": [
            "Subscription required"
          ],
          "availabilityCode": [
            "S"
          ],
          "documentStyle": [
            "doi"
          ],
          "site": [
            "DOI"
          ],
          "url": [
            "https://doi.org/10.3390/pharmaceutics13030387"
          ]
        },
        {
          "availability": [
            "Open access"
          ],
          "availabilityCode": [
            "OA"
          ],
          "documentStyle": [
            "html"
          ],
          "site": [
            "Europe_PMC"
          ],
          "url": [
            "https://europepmc.org/articles/PMC8000418"
          ]
        },
        {
          "availability": [
            "Open access"
          ],
          "availabilityCode": [
            "OA"
          ],
          "documentStyle": [
            "pdf"
          ],
          "site": [
            "Europe_PMC"
          ],
          "url": [
            "https://europepmc.org/articles/PMC8000418?pdf=render"
          ]
        }
      ]
    }
  ],
  "isOpenAccess": [
    "Y"
  ],
  "inEPMC": [
    "Y"
  ],
  "inPMC": [
    "N"
  ],
  "hasPDF": [
    "Y"
  ],
  "hasBook": [
    "N"
  ],
  "hasSuppl": [
    "N"
  ],
  "citedByCount": [
    "0"
  ],
  "hasData": [
    "N"
  ],
  "hasReferences": [
    "Y"
  ],
  "hasTextMinedTerms": [
    "Y"
  ],
  "hasDbCrossReferences": [
    "N"
  ],
  "hasLabsLinks": [
    "Y"
  ],
  "license": [
    "cc by"
  ],
  "authMan": [
    "N"
  ],
  "epmcAuthMan": [
    "N"
  ],
  "nihAuthMan": [
    "N"
  ],
  "hasTMAccessionNumbers": [
    "N"
  ],
  "dateOfCreation": [
    "2021-04-03"
  ],
  "firstIndexDate": [
    "2021-04-06"
  ],
  "fullTextReceivedDate": [
    "2021-03-29"
  ],
  "dateOfRevision": [
    "2021-04-13"
  ],
  "electronicPublicationDate": [
    "2021-03-13"
  ],
  "firstPublicationDate": [
    "2021-03-13"
  ]
}