<?xml version="1.0" encoding="UTF-8"?>
<ref id="ref-32">
 <label>Jung et al. (2017)</label>
 <element-citation publication-type="book">
  <person-group person-group-type="author">
   <name>
    <surname>Jung</surname>
    <given-names>SY</given-names>
   </name>
   <name>
    <surname>Lee</surname>
    <given-names>JW</given-names>
   </name>
   <name>
    <surname>Shin</surname>
    <given-names>HT</given-names>
   </name>
   <name>
    <surname>Kim</surname>
    <given-names>SJ</given-names>
   </name>
   <name>
    <surname>An</surname>
    <given-names>JB</given-names>
   </name>
   <name>
    <surname>Heo</surname>
    <given-names>TI</given-names>
   </name>
   <name>
    <surname>Chung</surname>
    <given-names>JM</given-names>
   </name>
   <name>
    <surname>Cho</surname>
    <given-names>YC</given-names>
   </name>
  </person-group>
  <year>2017</year>
  <source>Invasive Alien Plants in South Korea</source>
  <publisher-name>Korea National Arboretum</publisher-name>
  <publisher-loc>Pocheon</publisher-loc>
 </element-citation>
</ref>
