<?xml version="1.0" encoding="UTF-8"?>
<contrib-group>
 <contrib contrib-type="author">
  <name>
   <surname>Sairi</surname>
   <given-names>Anith M. M.</given-names>
  </name>
  <xref ref-type="aff" rid="I1">
   <sup>1</sup>
  </xref>
 </contrib>
 <contrib contrib-type="author">
  <name>
   <surname>Ismail</surname>
   <given-names>Siti Izera</given-names>
  </name>
  <xref ref-type="aff" rid="I1">
   <sup>1</sup>
  </xref>
 </contrib>
 <contrib contrib-type="author">
  <name>
   <surname>Sukor</surname>
   <given-names>Arina</given-names>
  </name>
  <xref ref-type="aff" rid="I2">
   <sup>2</sup>
  </xref>
 </contrib>
 <contrib contrib-type="author">
  <name>
   <surname>Rashid</surname>
   <given-names>Noraswati M. N.</given-names>
  </name>
  <xref ref-type="aff" rid="I3">
   <sup>3</sup>
  </xref>
 </contrib>
 <contrib contrib-type="author">
  <name>
   <surname>Saad</surname>
   <given-names>Norsazilawati</given-names>
  </name>
  <xref ref-type="aff" rid="I1">
   <sup>1</sup>
  </xref>
 </contrib>
 <contrib contrib-type="author">
  <name>
   <surname>Jamian</surname>
   <given-names>Syari</given-names>
  </name>
  <xref ref-type="aff" rid="I1">
   <sup>1</sup>
  </xref>
 </contrib>
 <contrib contrib-type="author" corresp="yes">
  <contrib-id contrib-id-type="orcid" authenticated="false">https://orcid.org/0000-0003-4882-3930</contrib-id>
  <name>
   <surname>Abdullah</surname>
   <given-names>Sumaiyah</given-names>
  </name>
  <email>sumaiyah@upm.edu.my</email>
  <xref ref-type="aff" rid="I1">
   <sup>1</sup>
  </xref>
 </contrib>
</contrib-group>
