<?xml version="1.0" encoding="UTF-8"?>
<table-wrap id="RSOS171424TB1" orientation="portrait" position="float" class="table-wrap">
 <label class="label">Table 1.</label>
 <caption class="caption">
  <p class="p">Comparative percentage compositions of the HD and HS-SPME extract from flowers, leaves and roots of 
   <italic class="italic">Echinops ilicifolius</italic>. Italics indicate the main components of each method.
  </p>
 </caption>
 <table frame="hsides" rules="groups" class="table">
  <colgroup span="1" class="colgroup">
   <col align="left" span="1" class="col"/>
   <col align="left" span="1" class="col"/>
   <col align="left" span="1" class="col"/>
   <col align="left" span="1" class="col"/>
   <col align="left" span="1" class="col"/>
   <col align="left" span="1" class="col"/>
   <col align="left" span="1" class="col"/>
   <col align="left" span="1" class="col"/>
  </colgroup>
  <thead valign="bottom" class="thead">
   <tr class="tr">
    <th rowspan="1" colspan="1" class="th"/>
    <th rowspan="1" colspan="1" class="th"/>
    <th colspan="2" align="left" rowspan="1" class="th">flower
     <hr class="hr"/>
    </th>
    <th colspan="2" align="left" rowspan="1" class="th">leaf
     <hr class="hr"/>
    </th>
    <th colspan="2" align="left" rowspan="1" class="th">root
     <hr class="hr"/>
    </th>
   </tr>
   <tr class="tr">
    <th align="left" rowspan="1" colspan="1" class="th">compounds</th>
    <th align="left" rowspan="1" colspan="1" class="th">RI
     <sup class="sup">a</sup>
    </th>
    <th align="left" rowspan="1" colspan="1" class="th">HD</th>
    <th align="left" rowspan="1" colspan="1" class="th">HS-SPME</th>
    <th align="left" rowspan="1" colspan="1" class="th">HD</th>
    <th align="left" rowspan="1" colspan="1" class="th">HS-SPME</th>
    <th align="left" rowspan="1" colspan="1" class="th">HD</th>
    <th align="left" rowspan="1" colspan="1" class="th">HS-SPME</th>
   </tr>
  </thead>
  <tbody class="tbody">
   <tr class="tr">
    <td rowspan="1" colspan="1" class="td">
     <italic class="italic">n</italic>-octane
    </td>
    <td rowspan="1" colspan="1" class="td">801</td>
    <td rowspan="1" colspan="1" class="td">—</td>
    <td rowspan="1" colspan="1" class="td">
     <italic class="italic">34.0</italic>
    </td>
    <td rowspan="1" colspan="1" class="td">—</td>
    <td rowspan="1" colspan="1" class="td">
     <italic class="italic">10.3</italic>
    </td>
    <td rowspan="1" colspan="1" class="td">—</td>
    <td rowspan="1" colspan="1" class="td">
     <italic class="italic">12.6</italic>
    </td>
   </tr>
   <tr class="tr">
    <td rowspan="1" colspan="1" class="td">(2
     <italic class="italic">E</italic>)-hexenal
    </td>
    <td rowspan="1" colspan="1" class="td">849</td>
    <td rowspan="1" colspan="1" class="td">—</td>
    <td rowspan="1" colspan="1" class="td">—</td>
    <td rowspan="1" colspan="1" class="td">—</td>
    <td rowspan="1" colspan="1" class="td">1.2</td>
    <td rowspan="1" colspan="1" class="td">—</td>
    <td rowspan="1" colspan="1" class="td">—</td>
   </tr>
   <tr class="tr">
    <td rowspan="1" colspan="1" class="td">
     <italic class="italic">n</italic>-hexanol
    </td>
    <td rowspan="1" colspan="1" class="td">862</td>
    <td rowspan="1" colspan="1" class="td">—</td>
    <td rowspan="1" colspan="1" class="td">—</td>
    <td rowspan="1" colspan="1" class="td">—</td>
    <td rowspan="1" colspan="1" class="td">—</td>
    <td rowspan="1" colspan="1" class="td">—</td>
    <td rowspan="1" colspan="1" class="td">2.9</td>
   </tr>
   <tr class="tr">
    <td rowspan="1" colspan="1" class="td">
     <italic class="italic">α</italic>-pinene
    </td>
    <td rowspan="1" colspan="1" class="td">932</td>
    <td rowspan="1" colspan="1" class="td">—</td>
    <td rowspan="1" colspan="1" class="td">4.1</td>
    <td rowspan="1" colspan="1" class="td">—</td>
    <td rowspan="1" colspan="1" class="td">
     <italic class="italic">5.9</italic>
    </td>
    <td rowspan="1" colspan="1" class="td">—</td>
    <td rowspan="1" colspan="1" class="td">3.3</td>
   </tr>
   <tr class="tr">
    <td rowspan="1" colspan="1" class="td">sabinene</td>
    <td rowspan="1" colspan="1" class="td">972</td>
    <td rowspan="1" colspan="1" class="td">—</td>
    <td rowspan="1" colspan="1" class="td">—</td>
    <td rowspan="1" colspan="1" class="td">—</td>
    <td rowspan="1" colspan="1" class="td">1.5</td>
    <td rowspan="1" colspan="1" class="td">—</td>
    <td rowspan="1" colspan="1" class="td">—</td>
   </tr>
   <tr class="tr">
    <td rowspan="1" colspan="1" class="td">
     <italic class="italic">β</italic>-pinene
    </td>
    <td rowspan="1" colspan="1" class="td">976</td>
    <td rowspan="1" colspan="1" class="td">—</td>
    <td rowspan="1" colspan="1" class="td">—</td>
    <td rowspan="1" colspan="1" class="td">—</td>
    <td rowspan="1" colspan="1" class="td">1.7</td>
    <td rowspan="1" colspan="1" class="td">—</td>
    <td rowspan="1" colspan="1" class="td">—</td>
   </tr>
   <tr class="tr">
    <td rowspan="1" colspan="1" class="td">1-decene</td>
    <td rowspan="1" colspan="1" class="td">988</td>
    <td rowspan="1" colspan="1" class="td">—</td>
    <td rowspan="1" colspan="1" class="td">—</td>
    <td rowspan="1" colspan="1" class="td">—</td>
    <td rowspan="1" colspan="1" class="td">—</td>
    <td rowspan="1" colspan="1" class="td">0.3</td>
    <td rowspan="1" colspan="1" class="td">—</td>
   </tr>
   <tr class="tr">
    <td rowspan="1" colspan="1" class="td">myrcene</td>
    <td rowspan="1" colspan="1" class="td">990</td>
    <td rowspan="1" colspan="1" class="td">0.1</td>
    <td rowspan="1" colspan="1" class="td">0.1</td>
    <td rowspan="1" colspan="1" class="td">0.1</td>
    <td rowspan="1" colspan="1" class="td">2.1</td>
    <td rowspan="1" colspan="1" class="td">—</td>
    <td rowspan="1" colspan="1" class="td">1.6</td>
   </tr>
   <tr class="tr">
    <td rowspan="1" colspan="1" class="td">
     <italic class="italic">n</italic>-decane
    </td>
    <td rowspan="1" colspan="1" class="td">998</td>
    <td rowspan="1" colspan="1" class="td">0.2</td>
    <td rowspan="1" colspan="1" class="td">
     <italic class="italic">25.1</italic>
    </td>
    <td rowspan="1" colspan="1" class="td">0.2</td>
    <td rowspan="1" colspan="1" class="td">
     <italic class="italic">32.6</italic>
    </td>
    <td rowspan="1" colspan="1" class="td">
     <italic class="italic">23.1</italic>
    </td>
    <td rowspan="1" colspan="1" class="td">
     <italic class="italic">12.6</italic>
    </td>
   </tr>
   <tr class="tr">
    <td rowspan="1" colspan="1" class="td">
     <italic class="italic">α</italic>-terpinene
    </td>
    <td rowspan="1" colspan="1" class="td">1015</td>
    <td rowspan="1" colspan="1" class="td">—</td>
    <td rowspan="1" colspan="1" class="td">—</td>
    <td rowspan="1" colspan="1" class="td">—</td>
    <td rowspan="1" colspan="1" class="td">0.8</td>
    <td rowspan="1" colspan="1" class="td">—</td>
    <td rowspan="1" colspan="1" class="td">—</td>
   </tr>
   <tr class="tr">
    <td rowspan="1" colspan="1" class="td">
     <italic class="italic">p</italic>-cymene
    </td>
    <td rowspan="1" colspan="1" class="td">1023</td>
    <td rowspan="1" colspan="1" class="td">—</td>
    <td rowspan="1" colspan="1" class="td">
     <italic class="italic">11.1</italic>
    </td>
    <td rowspan="1" colspan="1" class="td">—</td>
    <td rowspan="1" colspan="1" class="td">
     <italic class="italic">14.0</italic>
    </td>
    <td rowspan="1" colspan="1" class="td">0.9</td>
    <td rowspan="1" colspan="1" class="td">
     <italic class="italic">9.6</italic>
    </td>
   </tr>
   <tr class="tr">
    <td rowspan="1" colspan="1" class="td">limonene</td>
    <td rowspan="1" colspan="1" class="td">1027</td>
    <td rowspan="1" colspan="1" class="td">0.1</td>
    <td rowspan="1" colspan="1" class="td">4.4</td>
    <td rowspan="1" colspan="1" class="td">0.1</td>
    <td rowspan="1" colspan="1" class="td">
     <italic class="italic">9.2</italic>
    </td>
    <td rowspan="1" colspan="1" class="td">0.1</td>
    <td rowspan="1" colspan="1" class="td">4.1</td>
   </tr>
   <tr class="tr">
    <td rowspan="1" colspan="1" class="td">1,8-cineole</td>
    <td rowspan="1" colspan="1" class="td">1030</td>
    <td rowspan="1" colspan="1" class="td">0.1</td>
    <td rowspan="1" colspan="1" class="td">
     <italic class="italic">5.1</italic>
    </td>
    <td rowspan="1" colspan="1" class="td">—</td>
    <td rowspan="1" colspan="1" class="td">
     <italic class="italic">7.9</italic>
    </td>
    <td rowspan="1" colspan="1" class="td">—</td>
    <td rowspan="1" colspan="1" class="td">
     <italic class="italic">29.0</italic>
    </td>
   </tr>
   <tr class="tr">
    <td rowspan="1" colspan="1" class="td">(
     <italic class="italic">Z</italic>)-
     <italic class="italic">β</italic>-ocimene
    </td>
    <td rowspan="1" colspan="1" class="td">1035</td>
    <td rowspan="1" colspan="1" class="td">—</td>
    <td rowspan="1" colspan="1" class="td">—</td>
    <td rowspan="1" colspan="1" class="td">0.1</td>
    <td rowspan="1" colspan="1" class="td">0.1</td>
    <td rowspan="1" colspan="1" class="td">—</td>
    <td rowspan="1" colspan="1" class="td">—</td>
   </tr>
   <tr class="tr">
    <td rowspan="1" colspan="1" class="td">(
     <italic class="italic">E</italic>)-
     <italic class="italic">β</italic>-ocimene
    </td>
    <td rowspan="1" colspan="1" class="td">1045</td>
    <td rowspan="1" colspan="1" class="td">0.1</td>
    <td rowspan="1" colspan="1" class="td">—</td>
    <td rowspan="1" colspan="1" class="td">0.1</td>
    <td rowspan="1" colspan="1" class="td">0.1</td>
    <td rowspan="1" colspan="1" class="td">—</td>
    <td rowspan="1" colspan="1" class="td">—</td>
   </tr>
   <tr class="tr">
    <td rowspan="1" colspan="1" class="td">
     <italic class="italic">γ</italic>-terpinene
    </td>
    <td rowspan="1" colspan="1" class="td">1056</td>
    <td rowspan="1" colspan="1" class="td">—</td>
    <td rowspan="1" colspan="1" class="td">
     <italic class="italic">5.3</italic>
    </td>
    <td rowspan="1" colspan="1" class="td">—</td>
    <td rowspan="1" colspan="1" class="td">
     <italic class="italic">9.1</italic>
    </td>
    <td rowspan="1" colspan="1" class="td">0.8</td>
    <td rowspan="1" colspan="1" class="td">
     <italic class="italic">5.9</italic>
    </td>
   </tr>
   <tr class="tr">
    <td rowspan="1" colspan="1" class="td">
     <italic class="italic">trans</italic>-linalool oxide
    </td>
    <td rowspan="1" colspan="1" class="td">1070</td>
    <td rowspan="1" colspan="1" class="td">—</td>
    <td rowspan="1" colspan="1" class="td">—</td>
    <td rowspan="1" colspan="1" class="td">0.3</td>
    <td rowspan="1" colspan="1" class="td">—</td>
    <td rowspan="1" colspan="1" class="td">—</td>
    <td rowspan="1" colspan="1" class="td">—</td>
   </tr>
   <tr class="tr">
    <td rowspan="1" colspan="1" class="td">
     <italic class="italic">cis</italic>-linalool oxide
    </td>
    <td rowspan="1" colspan="1" class="td">1086</td>
    <td rowspan="1" colspan="1" class="td">0.1</td>
    <td rowspan="1" colspan="1" class="td">—</td>
    <td rowspan="1" colspan="1" class="td">0.3</td>
    <td rowspan="1" colspan="1" class="td">—</td>
    <td rowspan="1" colspan="1" class="td">—</td>
    <td rowspan="1" colspan="1" class="td">—</td>
   </tr>
   <tr class="tr">
    <td rowspan="1" colspan="1" class="td">linalool</td>
    <td rowspan="1" colspan="1" class="td">1098</td>
    <td rowspan="1" colspan="1" class="td">
     <italic class="italic">58.6</italic>
    </td>
    <td rowspan="1" colspan="1" class="td">
     <italic class="italic">10.7</italic>
    </td>
    <td rowspan="1" colspan="1" class="td">
     <italic class="italic">16</italic>
     <italic class="italic">.</italic>
     <italic class="italic">4</italic>
    </td>
    <td rowspan="1" colspan="1" class="td">1.5</td>
    <td rowspan="1" colspan="1" class="td">0.9</td>
    <td rowspan="1" colspan="1" class="td">3.7</td>
   </tr>
   <tr class="tr">
    <td rowspan="1" colspan="1" class="td">hotrienol</td>
    <td rowspan="1" colspan="1" class="td">1102</td>
    <td rowspan="1" colspan="1" class="td">—</td>
    <td rowspan="1" colspan="1" class="td">—</td>
    <td rowspan="1" colspan="1" class="td">0.1</td>
    <td rowspan="1" colspan="1" class="td">—</td>
    <td rowspan="1" colspan="1" class="td">—</td>
    <td rowspan="1" colspan="1" class="td">—</td>
   </tr>
   <tr class="tr">
    <td rowspan="1" colspan="1" class="td">
     <italic class="italic">n</italic>-nonanal
    </td>
    <td rowspan="1" colspan="1" class="td">1103</td>
    <td rowspan="1" colspan="1" class="td">—</td>
    <td rowspan="1" colspan="1" class="td">—</td>
    <td rowspan="1" colspan="1" class="td">—</td>
    <td rowspan="1" colspan="1" class="td">—</td>
    <td rowspan="1" colspan="1" class="td">0.2</td>
    <td rowspan="1" colspan="1" class="td">—</td>
   </tr>
   <tr class="tr">
    <td rowspan="1" colspan="1" class="td">
     <italic class="italic">trans</italic>-thujone
    </td>
    <td rowspan="1" colspan="1" class="td">1115</td>
    <td rowspan="1" colspan="1" class="td">—</td>
    <td rowspan="1" colspan="1" class="td">—</td>
    <td rowspan="1" colspan="1" class="td">—</td>
    <td rowspan="1" colspan="1" class="td">—</td>
    <td rowspan="1" colspan="1" class="td">—</td>
    <td rowspan="1" colspan="1" class="td">2.6</td>
   </tr>
   <tr class="tr">
    <td rowspan="1" colspan="1" class="td">methyl glutarate</td>
    <td rowspan="1" colspan="1" class="td">1135</td>
    <td rowspan="1" colspan="1" class="td">—</td>
    <td rowspan="1" colspan="1" class="td">—</td>
    <td rowspan="1" colspan="1" class="td">0.1</td>
    <td rowspan="1" colspan="1" class="td">—</td>
    <td rowspan="1" colspan="1" class="td">—</td>
    <td rowspan="1" colspan="1" class="td">—</td>
   </tr>
   <tr class="tr">
    <td rowspan="1" colspan="1" class="td">camphor</td>
    <td rowspan="1" colspan="1" class="td">1143</td>
    <td rowspan="1" colspan="1" class="td">—</td>
    <td rowspan="1" colspan="1" class="td">—</td>
    <td rowspan="1" colspan="1" class="td">0.1</td>
    <td rowspan="1" colspan="1" class="td">2.0</td>
    <td rowspan="1" colspan="1" class="td">0.6</td>
    <td rowspan="1" colspan="1" class="td">
     <italic class="italic">12.0</italic>
    </td>
   </tr>
   <tr class="tr">
    <td rowspan="1" colspan="1" class="td">(2
     <italic class="italic">E</italic>)-nonen-1-al
    </td>
    <td rowspan="1" colspan="1" class="td">1164</td>
    <td rowspan="1" colspan="1" class="td">Tr</td>
    <td rowspan="1" colspan="1" class="td">—</td>
    <td rowspan="1" colspan="1" class="td">—</td>
    <td rowspan="1" colspan="1" class="td">—</td>
    <td rowspan="1" colspan="1" class="td">—</td>
    <td rowspan="1" colspan="1" class="td">—</td>
   </tr>
   <tr class="tr">
    <td rowspan="1" colspan="1" class="td">terpinene-4-ol</td>
    <td rowspan="1" colspan="1" class="td">1175</td>
    <td rowspan="1" colspan="1" class="td">—</td>
    <td rowspan="1" colspan="1" class="td">—</td>
    <td rowspan="1" colspan="1" class="td">0.1</td>
    <td rowspan="1" colspan="1" class="td">—</td>
    <td rowspan="1" colspan="1" class="td">—</td>
    <td rowspan="1" colspan="1" class="td">—</td>
   </tr>
   <tr class="tr">
    <td rowspan="1" colspan="1" class="td">
     <italic class="italic">p</italic>-cymen-8-ol
    </td>
    <td rowspan="1" colspan="1" class="td">1184</td>
    <td rowspan="1" colspan="1" class="td">0.1</td>
    <td rowspan="1" colspan="1" class="td">—</td>
    <td rowspan="1" colspan="1" class="td">0.1</td>
    <td rowspan="1" colspan="1" class="td">—</td>
    <td rowspan="1" colspan="1" class="td">—</td>
    <td rowspan="1" colspan="1" class="td">—</td>
   </tr>
   <tr class="tr">
    <td rowspan="1" colspan="1" class="td">
     <italic class="italic">α</italic>-terpineol
    </td>
    <td rowspan="1" colspan="1" class="td">1188</td>
    <td rowspan="1" colspan="1" class="td">—</td>
    <td rowspan="1" colspan="1" class="td">—</td>
    <td rowspan="1" colspan="1" class="td">
     <italic class="italic">6</italic>
     <italic class="italic">.</italic>
     <italic class="italic">1</italic>
    </td>
    <td rowspan="1" colspan="1" class="td">—</td>
    <td rowspan="1" colspan="1" class="td">—</td>
    <td rowspan="1" colspan="1" class="td">—</td>
   </tr>
   <tr class="tr">
    <td rowspan="1" colspan="1" class="td">
     <italic class="italic">n</italic>-dodecane
    </td>
    <td rowspan="1" colspan="1" class="td">1197</td>
    <td rowspan="1" colspan="1" class="td">
     <italic class="italic">10.9</italic>
    </td>
    <td rowspan="1" colspan="1" class="td">—</td>
    <td rowspan="1" colspan="1" class="td">0.2</td>
    <td rowspan="1" colspan="1" class="td">—</td>
    <td rowspan="1" colspan="1" class="td">
     <italic class="italic">14.5</italic>
    </td>
    <td rowspan="1" colspan="1" class="td">—</td>
   </tr>
   <tr class="tr">
    <td rowspan="1" colspan="1" class="td">nerol</td>
    <td rowspan="1" colspan="1" class="td">1226</td>
    <td rowspan="1" colspan="1" class="td">
     <italic class="italic">5.4</italic>
    </td>
    <td rowspan="1" colspan="1" class="td">—</td>
    <td rowspan="1" colspan="1" class="td">2.6</td>
    <td rowspan="1" colspan="1" class="td">—</td>
    <td rowspan="1" colspan="1" class="td">—</td>
    <td rowspan="1" colspan="1" class="td">—</td>
   </tr>
   <tr class="tr">
    <td rowspan="1" colspan="1" class="td">neral</td>
    <td rowspan="1" colspan="1" class="td">1239</td>
    <td rowspan="1" colspan="1" class="td">—</td>
    <td rowspan="1" colspan="1" class="td">—</td>
    <td rowspan="1" colspan="1" class="td">0.1</td>
    <td rowspan="1" colspan="1" class="td">—</td>
    <td rowspan="1" colspan="1" class="td">—</td>
    <td rowspan="1" colspan="1" class="td">—</td>
   </tr>
   <tr class="tr">
    <td rowspan="1" colspan="1" class="td">geraniol</td>
    <td rowspan="1" colspan="1" class="td">1252</td>
    <td rowspan="1" colspan="1" class="td">
     <italic class="italic">17.4</italic>
    </td>
    <td rowspan="1" colspan="1" class="td">—</td>
    <td rowspan="1" colspan="1" class="td">
     <italic class="italic">8</italic>
     <italic class="italic">.</italic>
     <italic class="italic">3</italic>
    </td>
    <td rowspan="1" colspan="1" class="td">—</td>
    <td rowspan="1" colspan="1" class="td">—</td>
    <td rowspan="1" colspan="1" class="td">—</td>
   </tr>
   <tr class="tr">
    <td rowspan="1" colspan="1" class="td">geranial</td>
    <td rowspan="1" colspan="1" class="td">1268</td>
    <td rowspan="1" colspan="1" class="td">—</td>
    <td rowspan="1" colspan="1" class="td">—</td>
    <td rowspan="1" colspan="1" class="td">0.1</td>
    <td rowspan="1" colspan="1" class="td">—</td>
    <td rowspan="1" colspan="1" class="td">—</td>
    <td rowspan="1" colspan="1" class="td">—</td>
   </tr>
   <tr class="tr">
    <td rowspan="1" colspan="1" class="td">
     <italic class="italic">n</italic>-decanol
    </td>
    <td rowspan="1" colspan="1" class="td">1279</td>
    <td rowspan="1" colspan="1" class="td">0.1</td>
    <td rowspan="1" colspan="1" class="td">—</td>
    <td rowspan="1" colspan="1" class="td">—</td>
    <td rowspan="1" colspan="1" class="td">—</td>
    <td rowspan="1" colspan="1" class="td">0.2</td>
    <td rowspan="1" colspan="1" class="td">—</td>
   </tr>
   <tr class="tr">
    <td rowspan="1" colspan="1" class="td">thymol</td>
    <td rowspan="1" colspan="1" class="td">1291</td>
    <td rowspan="1" colspan="1" class="td">—</td>
    <td rowspan="1" colspan="1" class="td">—</td>
    <td rowspan="1" colspan="1" class="td">—</td>
    <td rowspan="1" colspan="1" class="td">—</td>
    <td rowspan="1" colspan="1" class="td">1.4</td>
    <td rowspan="1" colspan="1" class="td">—</td>
   </tr>
   <tr class="tr">
    <td rowspan="1" colspan="1" class="td">
     <italic class="italic">n</italic>-tridecane
    </td>
    <td rowspan="1" colspan="1" class="td">1297</td>
    <td rowspan="1" colspan="1" class="td">—</td>
    <td rowspan="1" colspan="1" class="td">—</td>
    <td rowspan="1" colspan="1" class="td">—</td>
    <td rowspan="1" colspan="1" class="td">—</td>
    <td rowspan="1" colspan="1" class="td">0.2</td>
    <td rowspan="1" colspan="1" class="td">—</td>
   </tr>
   <tr class="tr">
    <td rowspan="1" colspan="1" class="td">geranyl formate</td>
    <td rowspan="1" colspan="1" class="td">1298</td>
    <td rowspan="1" colspan="1" class="td">0.1</td>
    <td rowspan="1" colspan="1" class="td">—</td>
    <td rowspan="1" colspan="1" class="td">—</td>
    <td rowspan="1" colspan="1" class="td">—</td>
    <td rowspan="1" colspan="1" class="td">—</td>
    <td rowspan="1" colspan="1" class="td">—</td>
   </tr>
   <tr class="tr">
    <td rowspan="1" colspan="1" class="td">(2
     <italic class="italic">E</italic>,4
     <italic class="italic">E</italic>)-decadienal
    </td>
    <td rowspan="1" colspan="1" class="td">1321</td>
    <td rowspan="1" colspan="1" class="td">0.1</td>
    <td rowspan="1" colspan="1" class="td">—</td>
    <td rowspan="1" colspan="1" class="td">—</td>
    <td rowspan="1" colspan="1" class="td">—</td>
    <td rowspan="1" colspan="1" class="td">—</td>
    <td rowspan="1" colspan="1" class="td">—</td>
   </tr>
   <tr class="tr">
    <td rowspan="1" colspan="1" class="td">silphiperfol-4,7(14)-diene</td>
    <td rowspan="1" colspan="1" class="td">1363</td>
    <td rowspan="1" colspan="1" class="td">0.1</td>
    <td rowspan="1" colspan="1" class="td">—</td>
    <td rowspan="1" colspan="1" class="td">—</td>
    <td rowspan="1" colspan="1" class="td">—</td>
    <td rowspan="1" colspan="1" class="td">
     <italic class="italic">11.1</italic>
    </td>
    <td rowspan="1" colspan="1" class="td">—</td>
   </tr>
   <tr class="tr">
    <td rowspan="1" colspan="1" class="td">(
     <italic class="italic">E</italic>)-
     <italic class="italic">β</italic>-damascenone
    </td>
    <td rowspan="1" colspan="1" class="td">1382</td>
    <td rowspan="1" colspan="1" class="td">0.2</td>
    <td rowspan="1" colspan="1" class="td">—</td>
    <td rowspan="1" colspan="1" class="td">0.2</td>
    <td rowspan="1" colspan="1" class="td">—</td>
    <td rowspan="1" colspan="1" class="td">—</td>
    <td rowspan="1" colspan="1" class="td">—</td>
   </tr>
   <tr class="tr">
    <td rowspan="1" colspan="1" class="td">
     <italic class="italic">n</italic>-tetradecane
    </td>
    <td rowspan="1" colspan="1" class="td">1398</td>
    <td rowspan="1" colspan="1" class="td">0.1</td>
    <td rowspan="1" colspan="1" class="td">—</td>
    <td rowspan="1" colspan="1" class="td">0.1</td>
    <td rowspan="1" colspan="1" class="td">—</td>
    <td rowspan="1" colspan="1" class="td">
     <italic class="italic">5.3</italic>
    </td>
    <td rowspan="1" colspan="1" class="td">—</td>
   </tr>
   <tr class="tr">
    <td rowspan="1" colspan="1" class="td">(
     <italic class="italic">E</italic>)-
     <italic class="italic">β</italic>-damascone
    </td>
    <td rowspan="1" colspan="1" class="td">1412</td>
    <td rowspan="1" colspan="1" class="td">—</td>
    <td rowspan="1" colspan="1" class="td">—</td>
    <td rowspan="1" colspan="1" class="td">0.1</td>
    <td rowspan="1" colspan="1" class="td">—</td>
    <td rowspan="1" colspan="1" class="td">—</td>
    <td rowspan="1" colspan="1" class="td">—</td>
   </tr>
   <tr class="tr">
    <td rowspan="1" colspan="1" class="td">aromadendrene</td>
    <td rowspan="1" colspan="1" class="td">1436</td>
    <td rowspan="1" colspan="1" class="td">—</td>
    <td rowspan="1" colspan="1" class="td">—</td>
    <td rowspan="1" colspan="1" class="td">0.1</td>
    <td rowspan="1" colspan="1" class="td">—</td>
    <td rowspan="1" colspan="1" class="td">—</td>
    <td rowspan="1" colspan="1" class="td">—</td>
   </tr>
   <tr class="tr">
    <td rowspan="1" colspan="1" class="td">
     <italic class="italic">α</italic>-guaine
    </td>
    <td rowspan="1" colspan="1" class="td">1442</td>
    <td rowspan="1" colspan="1" class="td">0.1</td>
    <td rowspan="1" colspan="1" class="td">—</td>
    <td rowspan="1" colspan="1" class="td">—</td>
    <td rowspan="1" colspan="1" class="td">—</td>
    <td rowspan="1" colspan="1" class="td">3.3</td>
    <td rowspan="1" colspan="1" class="td">—</td>
   </tr>
   <tr class="tr">
    <td rowspan="1" colspan="1" class="td">geronyl acetone</td>
    <td rowspan="1" colspan="1" class="td">1451</td>
    <td rowspan="1" colspan="1" class="td">0.1</td>
    <td rowspan="1" colspan="1" class="td">—</td>
    <td rowspan="1" colspan="1" class="td">0.2</td>
    <td rowspan="1" colspan="1" class="td">—</td>
    <td rowspan="1" colspan="1" class="td">—</td>
    <td rowspan="1" colspan="1" class="td">—</td>
   </tr>
   <tr class="tr">
    <td rowspan="1" colspan="1" class="td">(
     <italic class="italic">E</italic>)-
     <italic class="italic">β</italic>-farnesene
    </td>
    <td rowspan="1" colspan="1" class="td">1460</td>
    <td rowspan="1" colspan="1" class="td">0.1</td>
    <td rowspan="1" colspan="1" class="td">—</td>
    <td rowspan="1" colspan="1" class="td">—</td>
    <td rowspan="1" colspan="1" class="td">—</td>
    <td rowspan="1" colspan="1" class="td">—</td>
    <td rowspan="1" colspan="1" class="td">—</td>
   </tr>
   <tr class="tr">
    <td rowspan="1" colspan="1" class="td">(
     <italic class="italic">E</italic>)-
     <italic class="italic">β</italic>-ionone
    </td>
    <td rowspan="1" colspan="1" class="td">1483</td>
    <td rowspan="1" colspan="1" class="td">0.1</td>
    <td rowspan="1" colspan="1" class="td">—</td>
    <td rowspan="1" colspan="1" class="td">0.5</td>
    <td rowspan="1" colspan="1" class="td">—</td>
    <td rowspan="1" colspan="1" class="td">—</td>
    <td rowspan="1" colspan="1" class="td">—</td>
   </tr>
   <tr class="tr">
    <td rowspan="1" colspan="1" class="td">
     <italic class="italic">n</italic>-pentadecane
    </td>
    <td rowspan="1" colspan="1" class="td">1497</td>
    <td rowspan="1" colspan="1" class="td">—</td>
    <td rowspan="1" colspan="1" class="td">—</td>
    <td rowspan="1" colspan="1" class="td">—</td>
    <td rowspan="1" colspan="1" class="td">—</td>
    <td rowspan="1" colspan="1" class="td">0.5</td>
    <td rowspan="1" colspan="1" class="td">—</td>
   </tr>
   <tr class="tr">
    <td rowspan="1" colspan="1" class="td">tridecanal</td>
    <td rowspan="1" colspan="1" class="td">1511</td>
    <td rowspan="1" colspan="1" class="td">0.2</td>
    <td rowspan="1" colspan="1" class="td">—</td>
    <td rowspan="1" colspan="1" class="td">—</td>
    <td rowspan="1" colspan="1" class="td">—</td>
    <td rowspan="1" colspan="1" class="td">—</td>
    <td rowspan="1" colspan="1" class="td">—</td>
   </tr>
   <tr class="tr">
    <td rowspan="1" colspan="1" class="td">
     <italic class="italic">trans</italic>-matricaria ester
    </td>
    <td rowspan="1" colspan="1" class="td">1529</td>
    <td rowspan="1" colspan="1" class="td">0.1</td>
    <td rowspan="1" colspan="1" class="td">—</td>
    <td rowspan="1" colspan="1" class="td">—</td>
    <td rowspan="1" colspan="1" class="td">—</td>
    <td rowspan="1" colspan="1" class="td">—</td>
    <td rowspan="1" colspan="1" class="td">—</td>
   </tr>
   <tr class="tr">
    <td rowspan="1" colspan="1" class="td">dodecanoic acid</td>
    <td rowspan="1" colspan="1" class="td">1562</td>
    <td rowspan="1" colspan="1" class="td">—</td>
    <td rowspan="1" colspan="1" class="td">—</td>
    <td rowspan="1" colspan="1" class="td">0.2</td>
    <td rowspan="1" colspan="1" class="td">—</td>
    <td rowspan="1" colspan="1" class="td">—</td>
    <td rowspan="1" colspan="1" class="td">—</td>
   </tr>
   <tr class="tr">
    <td rowspan="1" colspan="1" class="td">(3
     <italic class="italic">Z</italic>)-hexenyl benzoate
    </td>
    <td rowspan="1" colspan="1" class="td">1568</td>
    <td rowspan="1" colspan="1" class="td">0.1</td>
    <td rowspan="1" colspan="1" class="td">—</td>
    <td rowspan="1" colspan="1" class="td">3.3</td>
    <td rowspan="1" colspan="1" class="td">—</td>
    <td rowspan="1" colspan="1" class="td">1.3</td>
    <td rowspan="1" colspan="1" class="td">—</td>
   </tr>
   <tr class="tr">
    <td rowspan="1" colspan="1" class="td">globulol</td>
    <td rowspan="1" colspan="1" class="td">1581</td>
    <td rowspan="1" colspan="1" class="td">—</td>
    <td rowspan="1" colspan="1" class="td">—</td>
    <td rowspan="1" colspan="1" class="td">0.3</td>
    <td rowspan="1" colspan="1" class="td">—</td>
    <td rowspan="1" colspan="1" class="td">—</td>
    <td rowspan="1" colspan="1" class="td">—</td>
   </tr>
   <tr class="tr">
    <td rowspan="1" colspan="1" class="td">
     <italic class="italic">n</italic>-hexadecane
    </td>
    <td rowspan="1" colspan="1" class="td">1597</td>
    <td rowspan="1" colspan="1" class="td">0.2</td>
    <td rowspan="1" colspan="1" class="td">—</td>
    <td rowspan="1" colspan="1" class="td">0.3</td>
    <td rowspan="1" colspan="1" class="td">—</td>
    <td rowspan="1" colspan="1" class="td">2.5</td>
    <td rowspan="1" colspan="1" class="td">—</td>
   </tr>
   <tr class="tr">
    <td rowspan="1" colspan="1" class="td">tetradecanal</td>
    <td rowspan="1" colspan="1" class="td">1610</td>
    <td rowspan="1" colspan="1" class="td">—</td>
    <td rowspan="1" colspan="1" class="td">—</td>
    <td rowspan="1" colspan="1" class="td">0.5</td>
    <td rowspan="1" colspan="1" class="td">—</td>
    <td rowspan="1" colspan="1" class="td">—</td>
    <td rowspan="1" colspan="1" class="td">—</td>
   </tr>
   <tr class="tr">
    <td rowspan="1" colspan="1" class="td">selin-11-en-4-a-ol</td>
    <td rowspan="1" colspan="1" class="td">1657</td>
    <td rowspan="1" colspan="1" class="td">—</td>
    <td rowspan="1" colspan="1" class="td">—</td>
    <td rowspan="1" colspan="1" class="td">—</td>
    <td rowspan="1" colspan="1" class="td">—</td>
    <td rowspan="1" colspan="1" class="td">
     <italic class="italic">9.5</italic>
    </td>
    <td rowspan="1" colspan="1" class="td">—</td>
   </tr>
   <tr class="tr">
    <td rowspan="1" colspan="1" class="td">
     <italic class="italic">n</italic>-tetradecanol
    </td>
    <td rowspan="1" colspan="1" class="td">1674</td>
    <td rowspan="1" colspan="1" class="td">—</td>
    <td rowspan="1" colspan="1" class="td">—</td>
    <td rowspan="1" colspan="1" class="td">1.1</td>
    <td rowspan="1" colspan="1" class="td">—</td>
    <td rowspan="1" colspan="1" class="td">—</td>
    <td rowspan="1" colspan="1" class="td">—</td>
   </tr>
   <tr class="tr">
    <td rowspan="1" colspan="1" class="td">
     <italic class="italic">n</italic>-heptadecane
    </td>
    <td rowspan="1" colspan="1" class="td">1697</td>
    <td rowspan="1" colspan="1" class="td">—</td>
    <td rowspan="1" colspan="1" class="td">—</td>
    <td rowspan="1" colspan="1" class="td">0.4</td>
    <td rowspan="1" colspan="1" class="td">—</td>
    <td rowspan="1" colspan="1" class="td">—</td>
    <td rowspan="1" colspan="1" class="td">—</td>
   </tr>
   <tr class="tr">
    <td rowspan="1" colspan="1" class="td">pentadecanal</td>
    <td rowspan="1" colspan="1" class="td">1712</td>
    <td rowspan="1" colspan="1" class="td">0.1</td>
    <td rowspan="1" colspan="1" class="td">—</td>
    <td rowspan="1" colspan="1" class="td">1.9</td>
    <td rowspan="1" colspan="1" class="td">—</td>
    <td rowspan="1" colspan="1" class="td">—</td>
    <td rowspan="1" colspan="1" class="td">—</td>
   </tr>
   <tr class="tr">
    <td rowspan="1" colspan="1" class="td">tetradecanoic acid</td>
    <td rowspan="1" colspan="1" class="td">1761</td>
    <td rowspan="1" colspan="1" class="td">—</td>
    <td rowspan="1" colspan="1" class="td">—</td>
    <td rowspan="1" colspan="1" class="td">1.5</td>
    <td rowspan="1" colspan="1" class="td">—</td>
    <td rowspan="1" colspan="1" class="td">—</td>
    <td rowspan="1" colspan="1" class="td">—</td>
   </tr>
   <tr class="tr">
    <td rowspan="1" colspan="1" class="td">
     <italic class="italic">n</italic>-octadecane
    </td>
    <td rowspan="1" colspan="1" class="td">1797</td>
    <td rowspan="1" colspan="1" class="td">—</td>
    <td rowspan="1" colspan="1" class="td">—</td>
    <td rowspan="1" colspan="1" class="td">0.5</td>
    <td rowspan="1" colspan="1" class="td">—</td>
    <td rowspan="1" colspan="1" class="td">—</td>
    <td rowspan="1" colspan="1" class="td">—</td>
   </tr>
   <tr class="tr">
    <td rowspan="1" colspan="1" class="td">6,10,14-trimethyl-2-pentadecanone</td>
    <td rowspan="1" colspan="1" class="td">1841</td>
    <td rowspan="1" colspan="1" class="td">0.5</td>
    <td rowspan="1" colspan="1" class="td">—</td>
    <td rowspan="1" colspan="1" class="td">4.3</td>
    <td rowspan="1" colspan="1" class="td">—</td>
    <td rowspan="1" colspan="1" class="td">—</td>
    <td rowspan="1" colspan="1" class="td">—</td>
   </tr>
   <tr class="tr">
    <td rowspan="1" colspan="1" class="td">pentadecanoic acid</td>
    <td rowspan="1" colspan="1" class="td">1857</td>
    <td rowspan="1" colspan="1" class="td">0.2</td>
    <td rowspan="1" colspan="1" class="td">—</td>
    <td rowspan="1" colspan="1" class="td">1.6</td>
    <td rowspan="1" colspan="1" class="td">—</td>
    <td rowspan="1" colspan="1" class="td">—</td>
    <td rowspan="1" colspan="1" class="td">—</td>
   </tr>
   <tr class="tr">
    <td rowspan="1" colspan="1" class="td">di isobutyl phthalate</td>
    <td rowspan="1" colspan="1" class="td">1862</td>
    <td rowspan="1" colspan="1" class="td">—</td>
    <td rowspan="1" colspan="1" class="td">—</td>
    <td rowspan="1" colspan="1" class="td">1.9</td>
    <td rowspan="1" colspan="1" class="td">—</td>
    <td rowspan="1" colspan="1" class="td">—</td>
    <td rowspan="1" colspan="1" class="td">—</td>
   </tr>
   <tr class="tr">
    <td rowspan="1" colspan="1" class="td">methyl palmitate</td>
    <td rowspan="1" colspan="1" class="td">1921</td>
    <td rowspan="1" colspan="1" class="td">0.1</td>
    <td rowspan="1" colspan="1" class="td">—</td>
    <td rowspan="1" colspan="1" class="td">1.1</td>
    <td rowspan="1" colspan="1" class="td">—</td>
    <td rowspan="1" colspan="1" class="td">—</td>
    <td rowspan="1" colspan="1" class="td">—</td>
   </tr>
   <tr class="tr">
    <td rowspan="1" colspan="1" class="td">9-hexadecanoic acid</td>
    <td rowspan="1" colspan="1" class="td">1949</td>
    <td rowspan="1" colspan="1" class="td">—</td>
    <td rowspan="1" colspan="1" class="td">—</td>
    <td rowspan="1" colspan="1" class="td">—</td>
    <td rowspan="1" colspan="1" class="td">—</td>
    <td rowspan="1" colspan="1" class="td">1.5</td>
    <td rowspan="1" colspan="1" class="td">—</td>
   </tr>
   <tr class="tr">
    <td rowspan="1" colspan="1" class="td">
     <italic class="italic">n</italic>-hexadecanoic acid
    </td>
    <td rowspan="1" colspan="1" class="td">1968</td>
    <td rowspan="1" colspan="1" class="td">3.3</td>
    <td rowspan="1" colspan="1" class="td">—</td>
    <td rowspan="1" colspan="1" class="td">
     <italic class="italic">36</italic>
     <italic class="italic">.</italic>
     <italic class="italic">2</italic>
    </td>
    <td rowspan="1" colspan="1" class="td">—</td>
    <td rowspan="1" colspan="1" class="td">
     <italic class="italic">7.8</italic>
    </td>
    <td rowspan="1" colspan="1" class="td">—</td>
   </tr>
   <tr class="tr">
    <td rowspan="1" colspan="1" class="td">phytol</td>
    <td rowspan="1" colspan="1" class="td">2120</td>
    <td rowspan="1" colspan="1" class="td">0.1</td>
    <td rowspan="1" colspan="1" class="td">—</td>
    <td rowspan="1" colspan="1" class="td">4.9</td>
    <td rowspan="1" colspan="1" class="td">—</td>
    <td rowspan="1" colspan="1" class="td">—</td>
    <td rowspan="1" colspan="1" class="td">—</td>
   </tr>
   <tr class="tr">
    <td rowspan="1" colspan="1" class="td">linoneic acid</td>
    <td rowspan="1" colspan="1" class="td">2132</td>
    <td rowspan="1" colspan="1" class="td">0.6</td>
    <td rowspan="1" colspan="1" class="td">—</td>
    <td rowspan="1" colspan="1" class="td">0.8</td>
    <td rowspan="1" colspan="1" class="td">—</td>
    <td rowspan="1" colspan="1" class="td">2.5</td>
    <td rowspan="1" colspan="1" class="td">—</td>
   </tr>
   <tr class="tr">
    <td rowspan="1" colspan="1" class="td">oleic acid</td>
    <td rowspan="1" colspan="1" class="td">2145</td>
    <td rowspan="1" colspan="1" class="td">—</td>
    <td rowspan="1" colspan="1" class="td">—</td>
    <td rowspan="1" colspan="1" class="td">2.1</td>
    <td rowspan="1" colspan="1" class="td">—</td>
    <td rowspan="1" colspan="1" class="td">2.7</td>
    <td rowspan="1" colspan="1" class="td">—</td>
   </tr>
   <tr class="tr">
    <td rowspan="1" colspan="1" class="td">
     <italic class="italic">n</italic>-docosane
    </td>
    <td rowspan="1" colspan="1" class="td">2196</td>
    <td rowspan="1" colspan="1" class="td">Tr</td>
    <td rowspan="1" colspan="1" class="td">—</td>
    <td rowspan="1" colspan="1" class="td">—</td>
    <td rowspan="1" colspan="1" class="td">—</td>
    <td rowspan="1" colspan="1" class="td">—</td>
    <td rowspan="1" colspan="1" class="td">—</td>
   </tr>
   <tr class="tr">
    <td rowspan="1" colspan="1" class="td">monoterpene hydrocarbone</td>
    <td rowspan="1" colspan="1" class="td"/>
    <td rowspan="1" colspan="1" class="td">0.3</td>
    <td rowspan="1" colspan="1" class="td">25.0</td>
    <td rowspan="1" colspan="1" class="td">0.4</td>
    <td rowspan="1" colspan="1" class="td">44.5</td>
    <td rowspan="1" colspan="1" class="td">1.8</td>
    <td rowspan="1" colspan="1" class="td">24.5</td>
   </tr>
   <tr class="tr">
    <td rowspan="1" colspan="1" class="td">oxygenated monoterpenes</td>
    <td rowspan="1" colspan="1" class="td"/>
    <td rowspan="1" colspan="1" class="td">82.1</td>
    <td rowspan="1" colspan="1" class="td">15.8</td>
    <td rowspan="1" colspan="1" class="td">35.1</td>
    <td rowspan="1" colspan="1" class="td">11.4</td>
    <td rowspan="1" colspan="1" class="td">2.9</td>
    <td rowspan="1" colspan="1" class="td">47.3</td>
   </tr>
   <tr class="tr">
    <td rowspan="1" colspan="1" class="td">sesquiterpene hydrocarbones</td>
    <td rowspan="1" colspan="1" class="td"/>
    <td rowspan="1" colspan="1" class="td">0.2</td>
    <td rowspan="1" colspan="1" class="td">—</td>
    <td rowspan="1" colspan="1" class="td">0.1</td>
    <td rowspan="1" colspan="1" class="td">—</td>
    <td rowspan="1" colspan="1" class="td">3.3</td>
    <td rowspan="1" colspan="1" class="td">—</td>
   </tr>
   <tr class="tr">
    <td rowspan="1" colspan="1" class="td">oxygenated sesquiterpenes</td>
    <td rowspan="1" colspan="1" class="td"/>
    <td rowspan="1" colspan="1" class="td">0.1</td>
    <td rowspan="1" colspan="1" class="td">—</td>
    <td rowspan="1" colspan="1" class="td">0.8</td>
    <td rowspan="1" colspan="1" class="td">—</td>
    <td rowspan="1" colspan="1" class="td">9.5</td>
    <td rowspan="1" colspan="1" class="td">—</td>
   </tr>
   <tr class="tr">
    <td rowspan="1" colspan="1" class="td">other components</td>
    <td rowspan="1" colspan="1" class="td"/>
    <td rowspan="1" colspan="1" class="td">17.0</td>
    <td rowspan="1" colspan="1" class="td">59.2</td>
    <td rowspan="1" colspan="1" class="td">63.1</td>
    <td rowspan="1" colspan="1" class="td">44.0</td>
    <td rowspan="1" colspan="1" class="td">73.7</td>
    <td rowspan="1" colspan="1" class="td">28.1</td>
   </tr>
   <tr class="tr">
    <td rowspan="1" colspan="1" class="td">total</td>
    <td rowspan="1" colspan="1" class="td"/>
    <td rowspan="1" colspan="1" class="td">99.7</td>
    <td rowspan="1" colspan="1" class="td">100</td>
    <td rowspan="1" colspan="1" class="td">99.5</td>
    <td rowspan="1" colspan="1" class="td">99.9</td>
    <td rowspan="1" colspan="1" class="td">91.2</td>
    <td rowspan="1" colspan="1" class="td">99.9</td>
   </tr>
  </tbody>
 </table>
 <table-wrap-foot class="table-wrap-foot">
  <fn class="fn">
   <p class="p">
    <sup class="sup">a</sup>Retention indices as determined on a DB-5 column using a homologous serious of 
    <italic class="italic">n</italic>-alkanes.
   </p>
  </fn>
 </table-wrap-foot>
</table-wrap>
