<?xml version="1.0" encoding="UTF-8"?>
<ref id="CR31" class="ref">
 <span class="label" xmlns="http://www.w3.org/1999/xhtml">31.</span>
 <element-citation publication-type="journal" class="element-citation">
  <person-group person-group-type="author" class="person-group">
   <name class="name">
    <span class="surname" xmlns="http://www.w3.org/1999/xhtml">Centrone</span>
    <span class="given-names" xmlns="http://www.w3.org/1999/xhtml">A</span>
   </name>
  </person-group>
  <div class="article-title" xmlns="http://www.w3.org/1999/xhtml">Infrared imaging and spectroscopy beyond the diffraction limit</div>
  <div class="source" xmlns="http://www.w3.org/1999/xhtml">Annu. Rev. Anal. Chem.</div>
  <span class="year" xmlns="http://www.w3.org/1999/xhtml">2015</span>
  <span class="volume" xmlns="http://www.w3.org/1999/xhtml">8</span>
  <span class="fpage" xmlns="http://www.w3.org/1999/xhtml">101</span>
  <span class="lpage" xmlns="http://www.w3.org/1999/xhtml">126</span>
  <span pub-id-type="doi" class="pub-id" xmlns="http://www.w3.org/1999/xhtml">10.1146/annurev-anchem-071114-040435</span>
 </element-citation>
</ref>
