<?xml version="1.0" encoding="UTF-8"?>
<results title="country">
 <result pre="and contents of C. lansium EOs from China, Thailand, and" exact="Cuba" post="have been studied by hydrodistillation followed by gas chromatography-mass"/>
 <result pre="7.35%, respectively. In previous studies, EOs of C. lansium from" exact="China" post="[ 12], Thailand [ 13], and Cuba [ 14]"/>
 <result pre="previous studies, EOs of C. lansium from China [ 12]," exact="Thailand" post="[ 13], and Cuba [ 14] were obtained by"/>
 <result pre="C. lansium from China [ 12], Thailand [ 13], and" exact="Cuba" post="[ 14] were obtained by hydrodistillation and analyzed by"/>
 <result pre="used in the extraction of C. lansium leaves from Guangdong," exact="China" post="[ 18]. Thirty-six components were identified and the main"/>
 <result pre="analyzed the volatile components of fresh leaves and pericarps in" exact="Thailand" post="by headspce (HS) GC-MS. Thirty-nine components were identified in"/>
 <result pre="of leaves and pericarps of HLW and CHW in Hainan," exact="China" post="were classified into four clusters by cluster analysis. The"/>
 <result pre="Institutions of Hainan Province (Hnky2019-46); National Natural Science Foundation of" exact="China" post="(31860035). We thank JianPing Xu from Department of Biology,"/>
 <result pre="lansium Edible Medicinal And Non-Medicinal Plants 1st ed. Springer Berlin," exact="Germany" post="2012 871 883 6. Shen D.Y. Chao C. Chan"/>
 <result pre="10.1007/s11418-016-1033-x 27539584 10. collab: Chinese Academy of Sciences Flora of" exact="China" post="Science Press Beijing, China 1997 11. Wang X.H. Hua"/>
 <result pre="Chinese Academy of Sciences Flora of China Science Press Beijing," exact="China" post="1997 11. Wang X.H. Hua M. Chen Y.G. Comparison"/>
 <result pre="of traits of eleven yellow- wampee cultivars in Hainan South" exact="China" post="Fruits 2011 40 38 41 12. Zhao J.Y. Nan"/>
 <result pre="of the essential oils of Clausena lansium from Hainan island," exact="China" post="Z. Naturforsch C. 2004 59 153 156 10.1515/znc-2004-3-401 15241914"/>
 <result pre="Pino J.A. Marbot R. Fuentes V. Aromatic plants from western" exact="Cuba" post="IV. Composition of the leaf oils of Clausena lansium"/>
 <result pre="of Human Oral Yeast Species Distribution on Hainan Island in" exact="China" post="Mycopathologia 2013 176 359 368 10.1007/s11046-013-9703-7 24085613 17. Božović"/>
 <result pre="volatile oil and trace elements from fruits of Clausena lansium" exact="China" post="J. Chin. Mater. Med. 2006 31 898 900 19."/>
 <result pre="of eleven Piper species from distinct rainforest areas in Southeastern" exact="Brazil" post="Ind. Crop. Prod. 2016 94 528 539 10.1016/j.indcrop.2016.09.028 23."/>
</results>
