<?xml version="1.0" encoding="UTF-8"?>
<ref id="pone.0241190.ref025">
 <label>25</label>
 <mixed-citation publication-type="book">
  <name>
   <surname>Wynne</surname>
   <given-names>B</given-names>
  </name>. 
  <chapter-title>Public Understanding of Science</chapter-title> In: 
  <name>
   <surname>Jasanoff</surname>
   <given-names>S</given-names>
  </name>, editor. 
  <source>Handbook of Science and Technology Studies</source>. 
  <publisher-loc>Thousand Oaks, California</publisher-loc>: 
  <publisher-name>Sage Publications</publisher-name>; 
  <year>1995</year> p. 
  <fpage>361</fpage>–
  <lpage>88</lpage>.
 </mixed-citation>
</ref>
