<?xml version="1.0" encoding="UTF-8"?>
<results title="disease">
 <result pre="the positive effect of its extract on the treatment of" exact="denture stomatitis" post="due to Candida albicans.[ 27] The aim of the"/>
 <result pre="positive effect of its extract on the treatment of denture" exact="stomatitis" post="due to Candida albicans.[ 27] The aim of the"/>
 <result pre="with S. mutans being the most important etiologic agent for" exact="dental caries" post="pathogenicity and S. sanguis and S. salivarius as predominant"/>
 <result pre="a chlorhexidine mouthrinse on plaque, gingival inflammation and staining in" exact="gingivitis" post="patients: A systematic review J Clin Periodontol 2012 39"/>
 <result pre="essential oil of &quot; Satureja hortensis&quot; for the treatment of" exact="denture stomatitis" post="Dent Res J (Isfahan) 2012 9 198 202 22623938"/>
 <result pre="oil of &quot; Satureja hortensis&quot; for the treatment of denture" exact="stomatitis" post="Dent Res J (Isfahan) 2012 9 198 202 22623938"/>
 <result pre="95 16882158 29 MacFarlane TW Helnarska SJ The microbiology of" exact="angular cheilitis" post="Br Dent J 1976 140 403 6 1067101 30"/>
 <result pre="16882158 29 MacFarlane TW Helnarska SJ The microbiology of angular" exact="cheilitis" post="Br Dent J 1976 140 403 6 1067101 30"/>
</results>
