<?xml version="1.0" encoding="UTF-8"?>
<ref id="R07">
 <label>7</label>
 <element-citation publication-type="journal">
  <person-group person-group-type="author">
   <name>
    <surname> Talib</surname>
    <given-names>W</given-names>
   </name>
   <name>
    <surname>Mahasneh</surname>
    <given-names>A</given-names>
   </name>
  </person-group>
  <source>Scientia pharmaceutica </source>
  <year>2010</year>
  <volume>78</volume>
  <fpage>33</fpage>
  <?supplied-pmid 21179373?>
  <pub-id pub-id-type="pmid">21179373</pub-id>
 </element-citation>
</ref>
