{
  "id": [
    "31683894"
  ],
  "source": [
    "MED"
  ],
  "pmid": [
    "31683894"
  ],
  "pmcid": [
    "PMC6920853"
  ],
  "fullTextIdList": [
    {
      "fullTextId": [
        "PMC6920853"
      ]
    }
  ],
  "doi": [
    "10.3390/biom9110679"
  ],
  "title": [
    "Natural Products and Synthetic Analogs as a Source of Antitumor Drugs."
  ],
  "authorString": [
    "Sharifi-Rad J, Ozleyen A, Boyunegmez Tumer T, Oluwaseun Adetunji C, El Omari N, Balahbib A, Taheri Y, Bouyahya A, Martorell M, Martins N, Cho WC."
  ],
  "authorList": [
    {
      "author": [
        {
          "fullName": [
            "Sharifi-Rad J"
          ],
          "firstName": [
            "Javad"
          ],
          "lastName": [
            "Sharifi-Rad"
          ],
          "initials": [
            "J"
          ],
          "authorId": [
            {
              "_": "0000-0002-7301-8151",
              "$": {
                "type": "ORCID"
              }
            }
          ],
          "authorAffiliationDetailsList": [
            {
              "authorAffiliation": [
                {
                  "affiliation": [
                    "Zabol Medicinal Plants Research Center, Zabol University of Medical Sciences, Zabol 61615-585, Iran. javad.sharifirad@gmail.com."
                  ]
                }
              ]
            }
          ]
        },
        {
          "fullName": [
            "Ozleyen A"
          ],
          "firstName": [
            "Adem"
          ],
          "lastName": [
            "Ozleyen"
          ],
          "initials": [
            "A"
          ],
          "authorId": [
            {
              "_": "0000-0003-0195-3383",
              "$": {
                "type": "ORCID"
              }
            }
          ],
          "authorAffiliationDetailsList": [
            {
              "authorAffiliation": [
                {
                  "affiliation": [
                    "Graduate Program of Biomolecular Sciences, Institute of Natural and Applied Sciences, Canakkale Onsekiz Mart University, Canakkale 17020, Turkey. ademozleyen@gmail.com."
                  ]
                }
              ]
            }
          ]
        },
        {
          "fullName": [
            "Boyunegmez Tumer T"
          ],
          "firstName": [
            "Tugba"
          ],
          "lastName": [
            "Boyunegmez Tumer"
          ],
          "initials": [
            "T"
          ],
          "authorId": [
            {
              "_": "0000-0002-1740-4867",
              "$": {
                "type": "ORCID"
              }
            }
          ],
          "authorAffiliationDetailsList": [
            {
              "authorAffiliation": [
                {
                  "affiliation": [
                    "Department of Molecular Biology and Genetics, Faculty of Arts and Science, Canakkale Onsekiz Mart University, Canakkale 17020, Turkey. tumertb@gmail.com."
                  ]
                }
              ]
            }
          ]
        },
        {
          "fullName": [
            "Oluwaseun Adetunji C"
          ],
          "firstName": [
            "Charles"
          ],
          "lastName": [
            "Oluwaseun Adetunji"
          ],
          "initials": [
            "C"
          ],
          "authorAffiliationDetailsList": [
            {
              "authorAffiliation": [
                {
                  "affiliation": [
                    "Applied Microbiology, Biotechnology and Nanotechnology Laboratory, Department of Microbiology, Edo University, Iyamho, Edo State 300271, Nigeria. adetunji.charles@edouniversity.edu.ng."
                  ]
                }
              ]
            }
          ]
        },
        {
          "fullName": [
            "El Omari N"
          ],
          "firstName": [
            "Nasreddine"
          ],
          "lastName": [
            "El Omari"
          ],
          "initials": [
            "N"
          ],
          "authorId": [
            {
              "_": "0000-0002-0308-1155",
              "$": {
                "type": "ORCID"
              }
            }
          ],
          "authorAffiliationDetailsList": [
            {
              "authorAffiliation": [
                {
                  "affiliation": [
                    "Laboratory of Histology, Embryology and Cytogenetic, Faculty of Medicine and Pharmacy, Mohammed V University, Rabat 10100, Morocco. nasrelomari@gmail.com."
                  ]
                }
              ]
            }
          ]
        },
        {
          "fullName": [
            "Balahbib A"
          ],
          "firstName": [
            "Abdelaali"
          ],
          "lastName": [
            "Balahbib"
          ],
          "initials": [
            "A"
          ],
          "authorId": [
            {
              "_": "0000-0002-9024-4898",
              "$": {
                "type": "ORCID"
              }
            }
          ],
          "authorAffiliationDetailsList": [
            {
              "authorAffiliation": [
                {
                  "affiliation": [
                    "Laboratory of Zoology and General Biology, Faculty of Sciences, Mohammed V University, Rabat 10106, Morocco. balahbib.abdo@gmail.com."
                  ]
                }
              ]
            }
          ]
        },
        {
          "fullName": [
            "Taheri Y"
          ],
          "firstName": [
            "Yasaman"
          ],
          "lastName": [
            "Taheri"
          ],
          "initials": [
            "Y"
          ],
          "authorId": [
            {
              "_": "0000-0002-0836-236X",
              "$": {
                "type": "ORCID"
              }
            }
          ],
          "authorAffiliationDetailsList": [
            {
              "authorAffiliation": [
                {
                  "affiliation": [
                    "Phytochemistry Research Center, Shahid Beheshti University of Medical Sciences, Tehran 1991953381, Iran. taaheri.yasaman@gmail.com."
                  ]
                },
                {
                  "affiliation": [
                    "Department of Pharmacology and Toxicology, School of Pharmacy, Shahid Beheshti University of Medical Sciences, Tehran 11369, Iran. taaheri.yasaman@gmail.com."
                  ]
                }
              ]
            }
          ]
        },
        {
          "fullName": [
            "Bouyahya A"
          ],
          "firstName": [
            "Abdelhakim"
          ],
          "lastName": [
            "Bouyahya"
          ],
          "initials": [
            "A"
          ],
          "authorId": [
            {
              "_": "0000-0001-9317-1631",
              "$": {
                "type": "ORCID"
              }
            }
          ],
          "authorAffiliationDetailsList": [
            {
              "authorAffiliation": [
                {
                  "affiliation": [
                    "Laboratory of Human Pathologies Biology, Department of Biology, Faculty of Sciences, and Genomic Center of Human Pathologies, Faculty of Medicine and Pharmacy, Mohammed V University, Rabat 10106, Morocco. boyahyaa-90@hotmail.fr."
                  ]
                }
              ]
            }
          ]
        },
        {
          "fullName": [
            "Martorell M"
          ],
          "firstName": [
            "Miquel"
          ],
          "lastName": [
            "Martorell"
          ],
          "initials": [
            "M"
          ],
          "authorId": [
            {
              "_": "0000-0003-3183-7623",
              "$": {
                "type": "ORCID"
              }
            }
          ],
          "authorAffiliationDetailsList": [
            {
              "authorAffiliation": [
                {
                  "affiliation": [
                    "Department of Nutrition and Dietetics, Faculty of Pharmacy, University of Concepcion, Concepcion 4070386, Chile. mmartorell@udec.cl."
                  ]
                },
                {
                  "affiliation": [
                    "Universidad de Concepci칩n, Unidad de Desarrollo Tecnol칩gico, UDT, Concepcion 4070386, Chile. mmartorell@udec.cl."
                  ]
                }
              ]
            }
          ]
        },
        {
          "fullName": [
            "Martins N"
          ],
          "firstName": [
            "Nat치lia"
          ],
          "lastName": [
            "Martins"
          ],
          "initials": [
            "N"
          ],
          "authorId": [
            {
              "_": "0000-0002-5934-5201",
              "$": {
                "type": "ORCID"
              }
            }
          ],
          "authorAffiliationDetailsList": [
            {
              "authorAffiliation": [
                {
                  "affiliation": [
                    "Faculty of Medicine, University of Porto, Alameda Prof. Hern칙ni Monteiro, 4200-319 Porto, Portugal. ncmartins@med.up.pt."
                  ]
                },
                {
                  "affiliation": [
                    "Institute for Research and Innovation in Health (i3S), University of Porto, 4200-135 Porto, Portugal. ncmartins@med.up.pt."
                  ]
                }
              ]
            }
          ]
        },
        {
          "fullName": [
            "Cho WC"
          ],
          "firstName": [
            "William C"
          ],
          "lastName": [
            "Cho"
          ],
          "initials": [
            "WC"
          ],
          "authorId": [
            {
              "_": "0000-0003-4174-4586",
              "$": {
                "type": "ORCID"
              }
            }
          ],
          "authorAffiliationDetailsList": [
            {
              "authorAffiliation": [
                {
                  "affiliation": [
                    "Department of Clinical Oncology, Queen Elizabeth Hospital, Hong Kong, China. chocs@ha.org.hk."
                  ]
                }
              ]
            }
          ]
        }
      ]
    }
  ],
  "authorIdList": [
    {
      "authorId": [
        {
          "_": "0000-0001-9317-1631",
          "$": {
            "type": "ORCID"
          }
        },
        {
          "_": "0000-0002-0308-1155",
          "$": {
            "type": "ORCID"
          }
        },
        {
          "_": "0000-0002-0836-236X",
          "$": {
            "type": "ORCID"
          }
        },
        {
          "_": "0000-0002-1740-4867",
          "$": {
            "type": "ORCID"
          }
        },
        {
          "_": "0000-0002-5934-5201",
          "$": {
            "type": "ORCID"
          }
        },
        {
          "_": "0000-0002-7301-8151",
          "$": {
            "type": "ORCID"
          }
        },
        {
          "_": "0000-0002-9024-4898",
          "$": {
            "type": "ORCID"
          }
        },
        {
          "_": "0000-0003-0195-3383",
          "$": {
            "type": "ORCID"
          }
        },
        {
          "_": "0000-0003-3183-7623",
          "$": {
            "type": "ORCID"
          }
        },
        {
          "_": "0000-0003-3524-6441",
          "$": {
            "type": "ORCID"
          }
        },
        {
          "_": "0000-0003-4174-4586",
          "$": {
            "type": "ORCID"
          }
        }
      ]
    }
  ],
  "dataLinksTagsList": [
    {
      "dataLinkstag": [
        "altmetrics"
      ]
    }
  ],
  "journalInfo": [
    {
      "issue": [
        "11"
      ],
      "volume": [
        "9"
      ],
      "journalIssueId": [
        "2877555"
      ],
      "dateOfPublication": [
        "2019 Nov"
      ],
      "monthOfPublication": [
        "11"
      ],
      "yearOfPublication": [
        "2019"
      ],
      "printPublicationDate": [
        "2019-11-01"
      ],
      "journal": [
        {
          "title": [
            "Biomolecules"
          ],
          "ISOAbbreviation": [
            "Biomolecules"
          ],
          "medlineAbbreviation": [
            "Biomolecules"
          ],
          "NLMid": [
            "101596414"
          ],
          "ISSN": [
            "2218-273X"
          ],
          "ESSN": [
            "2218-273X"
          ]
        }
      ]
    }
  ],
  "pubYear": [
    "2019"
  ],
  "abstractText": [
    "Cancer is a heterogeneous disease and one of the major issues of health concern, especially for the public health system globally. Nature is a source of anticancer drugs with abundant pool of diverse chemicals and pharmacologically active compounds. In recent decade, some natural products and synthetic analogs have been investigated for the cancer treatment. This article presents the utilization of natural products as a source of antitumor drugs."
  ],
  "affiliation": [
    "Zabol Medicinal Plants Research Center, Zabol University of Medical Sciences, Zabol 61615-585, Iran. javad.sharifirad@gmail.com."
  ],
  "publicationStatus": [
    "epublish"
  ],
  "language": [
    "eng"
  ],
  "pubModel": [
    "Electronic"
  ],
  "pubTypeList": [
    {
      "pubType": [
        "Research Support, Non-U.S. Gov't",
        "review-article",
        "Review",
        "Journal Article"
      ]
    }
  ],
  "meshHeadingList": [
    {
      "meshHeading": [
        {
          "majorTopic_YN": [
            "N"
          ],
          "descriptorName": [
            "Animals"
          ]
        },
        {
          "majorTopic_YN": [
            "N"
          ],
          "descriptorName": [
            "Humans"
          ]
        },
        {
          "majorTopic_YN": [
            "N"
          ],
          "descriptorName": [
            "Antineoplastic Agents"
          ],
          "meshQualifierList": [
            {
              "meshQualifier": [
                {
                  "abbreviation": [
                    "CS"
                  ],
                  "qualifierName": [
                    "chemical synthesis"
                  ],
                  "majorTopic_YN": [
                    "N"
                  ]
                },
                {
                  "abbreviation": [
                    "PD"
                  ],
                  "qualifierName": [
                    "pharmacology"
                  ],
                  "majorTopic_YN": [
                    "Y"
                  ]
                },
                {
                  "abbreviation": [
                    "CH"
                  ],
                  "qualifierName": [
                    "chemistry"
                  ],
                  "majorTopic_YN": [
                    "Y"
                  ]
                }
              ]
            }
          ]
        },
        {
          "majorTopic_YN": [
            "N"
          ],
          "descriptorName": [
            "Biological Products"
          ],
          "meshQualifierList": [
            {
              "meshQualifier": [
                {
                  "abbreviation": [
                    "CS"
                  ],
                  "qualifierName": [
                    "chemical synthesis"
                  ],
                  "majorTopic_YN": [
                    "N"
                  ]
                },
                {
                  "abbreviation": [
                    "PD"
                  ],
                  "qualifierName": [
                    "pharmacology"
                  ],
                  "majorTopic_YN": [
                    "Y"
                  ]
                },
                {
                  "abbreviation": [
                    "CH"
                  ],
                  "qualifierName": [
                    "chemistry"
                  ],
                  "majorTopic_YN": [
                    "Y"
                  ]
                }
              ]
            }
          ]
        },
        {
          "majorTopic_YN": [
            "N"
          ],
          "descriptorName": [
            "Drug Approval"
          ]
        }
      ]
    }
  ],
  "keywordList": [
    {
      "keyword": [
        "Anticancer",
        "Natural products",
        "Phytomedicine",
        "Phytochemical"
      ]
    }
  ],
  "chemicalList": [
    {
      "chemical": [
        {
          "name": [
            "Antineoplastic Agents"
          ],
          "registryNumber": [
            "0"
          ]
        },
        {
          "name": [
            "Biological Products"
          ],
          "registryNumber": [
            "0"
          ]
        }
      ]
    }
  ],
  "subsetList": [
    {
      "subset": [
        {
          "code": [
            "IM"
          ],
          "name": [
            "Index Medicus"
          ]
        }
      ]
    }
  ],
  "fullTextUrlList": [
    {
      "fullTextUrl": [
        {
          "availability": [
            "Subscription required"
          ],
          "availabilityCode": [
            "S"
          ],
          "documentStyle": [
            "doi"
          ],
          "site": [
            "DOI"
          ],
          "url": [
            "https://doi.org/10.3390/biom9110679"
          ]
        },
        {
          "availability": [
            "Open access"
          ],
          "availabilityCode": [
            "OA"
          ],
          "documentStyle": [
            "html"
          ],
          "site": [
            "Europe_PMC"
          ],
          "url": [
            "https://europepmc.org/articles/PMC6920853"
          ]
        },
        {
          "availability": [
            "Open access"
          ],
          "availabilityCode": [
            "OA"
          ],
          "documentStyle": [
            "pdf"
          ],
          "site": [
            "Europe_PMC"
          ],
          "url": [
            "https://europepmc.org/articles/PMC6920853?pdf=render"
          ]
        }
      ]
    }
  ],
  "isOpenAccess": [
    "Y"
  ],
  "inEPMC": [
    "Y"
  ],
  "inPMC": [
    "N"
  ],
  "hasPDF": [
    "Y"
  ],
  "hasBook": [
    "N"
  ],
  "hasSuppl": [
    "N"
  ],
  "citedByCount": [
    "7"
  ],
  "hasData": [
    "N"
  ],
  "hasReferences": [
    "Y"
  ],
  "hasTextMinedTerms": [
    "Y"
  ],
  "hasDbCrossReferences": [
    "N"
  ],
  "hasLabsLinks": [
    "Y"
  ],
  "license": [
    "cc by"
  ],
  "authMan": [
    "N"
  ],
  "epmcAuthMan": [
    "N"
  ],
  "nihAuthMan": [
    "N"
  ],
  "hasTMAccessionNumbers": [
    "N"
  ],
  "dateOfCompletion": [
    "2020-09-02"
  ],
  "dateOfCreation": [
    "2019-11-06"
  ],
  "firstIndexDate": [
    "2019-11-05"
  ],
  "fullTextReceivedDate": [
    "2020-07-12"
  ],
  "dateOfRevision": [
    "2020-09-02"
  ],
  "electronicPublicationDate": [
    "2019-11-01"
  ],
  "firstPublicationDate": [
    "2019-11-01"
  ]
}