<?xml version="1.0" encoding="UTF-8"?>
<contrib-group class="contrib-group">
 <contrib contrib-type="author" class="contrib">
  <name class="name">
   <surname class="surname">Bampali</surname>
   <given-names class="given-names">Evangelia</given-names>
  </name>
  <xref ref-type="aff" rid="I1" class="xref"/>
 </contrib>
 <contrib contrib-type="author" class="contrib">
  <name class="name">
   <surname class="surname">Graikou</surname>
   <given-names class="given-names">Konstantia</given-names>
  </name>
  <xref ref-type="aff" rid="I1" class="xref"/>
 </contrib>
 <contrib contrib-type="author" class="contrib">
  <name class="name">
   <surname class="surname">Aligiannis</surname>
   <given-names class="given-names">Nektarios</given-names>
  </name>
  <xref ref-type="aff" rid="I1" class="xref"/>
 </contrib>
 <contrib contrib-type="author" corresp="yes" class="contrib">
  <span contrib-id-type="orcid" authenticated="false" class="contrib-id" xmlns="http://www.w3.org/1999/xhtml">http://orcid.org/0000-0002-6816-5261</span>
  <name class="name">
   <surname class="surname">Chinou</surname>
   <given-names class="given-names">Ioanna</given-names>
  </name>
  <span class="email" xmlns="http://www.w3.org/1999/xhtml">ichinou@pharm.uoa.gr</span>
  <xref ref-type="aff" rid="I1" class="xref"/>
 </contrib>
</contrib-group>
