<?xml version="1.0" encoding="UTF-8"?>
<ref id="B135" class="ref">
 <span class="label" xmlns="http://www.w3.org/1999/xhtml">135</span>
 <element-citation publication-type="journal" class="element-citation">
  <person-group person-group-type="author" class="person-group">
   <name class="name">
    <span class="surname" xmlns="http://www.w3.org/1999/xhtml">Figueirinha</span>
    <span class="given-names" xmlns="http://www.w3.org/1999/xhtml">A</span>
   </name>
   <name class="name">
    <span class="surname" xmlns="http://www.w3.org/1999/xhtml">Paranhos</span>
    <span class="given-names" xmlns="http://www.w3.org/1999/xhtml">A</span>
   </name>
   <name class="name">
    <span class="surname" xmlns="http://www.w3.org/1999/xhtml">Perez-Alonso</span>
    <span class="given-names" xmlns="http://www.w3.org/1999/xhtml">JJ</span>
   </name>
   <name class="name">
    <span class="surname" xmlns="http://www.w3.org/1999/xhtml">Santos-Buelga</span>
    <span class="given-names" xmlns="http://www.w3.org/1999/xhtml">C</span>
   </name>
   <name class="name">
    <span class="surname" xmlns="http://www.w3.org/1999/xhtml">Batista</span>
    <span class="given-names" xmlns="http://www.w3.org/1999/xhtml">MT</span>
   </name>
  </person-group>
  <div class="article-title" xmlns="http://www.w3.org/1999/xhtml">
   <span class="italic">Cymbopogon citratus</span> leaves: characterization of flavonoids by HPLC–PDA–ESI/MS/MS and an approach to their potential as a source of bioactive polyphenols
  </div>
  <div class="source" xmlns="http://www.w3.org/1999/xhtml">
   <span class="italic">Food Chem.</span>
  </div>
  <span class="volume" xmlns="http://www.w3.org/1999/xhtml">110</span>
  <span class="fpage" xmlns="http://www.w3.org/1999/xhtml">718</span>
  <span class="lpage" xmlns="http://www.w3.org/1999/xhtml">728</span>
  <span class="year" xmlns="http://www.w3.org/1999/xhtml">2008</span>
 </element-citation>
</ref>
