<?xml version="1.0" encoding="UTF-8"?>
<contrib-group class="contrib-group">
 <contrib contrib-type="author" class="contrib">
  <name class="name">
   <surname class="surname">Chen</surname>
   <given-names class="given-names">Chang-Chih</given-names>
  </name>
  <xref ref-type="aff" rid="af1-ijms-20-02579" class="xref">1</xref>
  <xref ref-type="aff" rid="af2-ijms-20-02579" class="xref">2</xref>
 </contrib>
 <contrib contrib-type="author" class="contrib">
  <name class="name">
   <surname class="surname">Nien</surname>
   <given-names class="given-names">Chia-Jen</given-names>
  </name>
  <xref ref-type="aff" rid="af3-ijms-20-02579" class="xref">3</xref>
 </contrib>
 <contrib contrib-type="author" class="contrib">
  <name class="name">
   <surname class="surname">Chen</surname>
   <given-names class="given-names">Lih-Geeng</given-names>
  </name>
  <xref ref-type="aff" rid="af4-ijms-20-02579" class="xref">4</xref>
 </contrib>
 <contrib contrib-type="author" class="contrib">
  <name class="name">
   <surname class="surname">Huang</surname>
   <given-names class="given-names">Kuen-Yu</given-names>
  </name>
  <xref ref-type="aff" rid="af3-ijms-20-02579" class="xref">3</xref>
 </contrib>
 <contrib contrib-type="author" class="contrib">
  <name class="name">
   <surname class="surname">Chang</surname>
   <given-names class="given-names">Wei-Jen</given-names>
  </name>
  <xref ref-type="aff" rid="af5-ijms-20-02579" class="xref">5</xref>
 </contrib>
 <contrib contrib-type="author" class="contrib">
  <contrib-id contrib-id-type="orcid" authenticated="true" class="contrib-id">https://orcid.org/0000-0003-4184-3744</contrib-id>
  <name class="name">
   <surname class="surname">Huang</surname>
   <given-names class="given-names">Haw-Ming</given-names>
  </name>
  <xref ref-type="aff" rid="af3-ijms-20-02579" class="xref">3</xref>
  <xref ref-type="aff" rid="af5-ijms-20-02579" class="xref">5</xref>
  <xref rid="c1-ijms-20-02579" ref-type="corresp" class="xref">*</xref>
 </contrib>
</contrib-group>
