<?xml version="1.0" encoding="UTF-8"?>
<results title="frequencies">
 <result title="frequency" count="28">Cleistocalyx operculatus</result>
 <result title="frequency" count="13">Staphylococcus aureus</result>
 <result title="frequency" count="8">Pistacia aeruginosa</result>
 <result title="frequency" count="1">Calophyllum inophyllum</result>
 <result title="frequency" count="1">Datura alba</result>
 <result title="frequency" count="1">S. aureus</result>
 <result title="frequency" count="1">Pistacia lentiscus</result>
 <result title="frequency" count="1">Nigella sativa</result>
 <result title="frequency" count="1">Achillea millefolium</result>
 <result title="frequency" count="1">Pseudomonas aeruginosa</result>
 <result title="frequency" count="1">Aloe vera</result>
 <result title="frequency" count="1">Carica papaya</result>
</results>
