{
  "id": [
    "29977171"
  ],
  "source": [
    "MED"
  ],
  "pmid": [
    "29977171"
  ],
  "pmcid": [
    "PMC6011056"
  ],
  "doi": [
    "10.1155/2018/7405736"
  ],
  "title": [
    "Antibacterial and Antibiofilm Activities of Cinnamomum Sp. Essential Oil and Cinnamaldehyde: Antimicrobial Activities."
  ],
  "authorString": [
    "Firmino DF, Cavalcante TTA, Gomes GA, Firmino NCS, Rosa LD, de Carvalho MG, Catunda FEA."
  ],
  "authorList": [
    {
      "author": [
        {
          "fullName": [
            "Firmino DF"
          ],
          "firstName": [
            "Diego F"
          ],
          "lastName": [
            "Firmino"
          ],
          "initials": [
            "DF"
          ],
          "affiliation": [
            "University Center UNINTA, Exact Sciences Center, Sobral, CE, Brazil."
          ]
        },
        {
          "fullName": [
            "Cavalcante TTA"
          ],
          "firstName": [
            "Theodora T A"
          ],
          "lastName": [
            "Cavalcante"
          ],
          "initials": [
            "TTA"
          ],
          "affiliation": [
            "University Center UNINTA, Medical Sciences Center, Sobral, CE, Brazil."
          ]
        },
        {
          "fullName": [
            "Gomes GA"
          ],
          "firstName": [
            "Geovany A"
          ],
          "lastName": [
            "Gomes"
          ],
          "initials": [
            "GA"
          ],
          "affiliation": [
            "Acarau Valley State University, Center for Science and Technology, Sobral, CE, Brazil."
          ]
        },
        {
          "fullName": [
            "Firmino NCS"
          ],
          "firstName": [
            "Nairley C S"
          ],
          "lastName": [
            "Firmino"
          ],
          "initials": [
            "NCS"
          ],
          "affiliation": [
            "University Center UNINTA, Health Sciences Center, Sobral, CE, Brazil."
          ]
        },
        {
          "fullName": [
            "Rosa LD"
          ],
          "firstName": [
            "Lucas D"
          ],
          "lastName": [
            "Rosa"
          ],
          "initials": [
            "LD"
          ],
          "affiliation": [
            "University Center UNINTA, Health Sciences Center, Sobral, CE, Brazil."
          ]
        },
        {
          "fullName": [
            "de Carvalho MG"
          ],
          "firstName": [
            "Mário G"
          ],
          "lastName": [
            "de Carvalho"
          ],
          "initials": [
            "MG"
          ],
          "affiliation": [
            "Federal Rural University of Rio de Janeiro, Exact Sciences Center, Seropédica, RJ, Brazil."
          ]
        },
        {
          "fullName": [
            "Catunda FEA Jr"
          ],
          "firstName": [
            "Francisco E A"
          ],
          "lastName": [
            "Catunda"
          ],
          "initials": [
            "FEA"
          ],
          "authorId": [
            {
              "_": "0000-0002-8089-730X",
              "$": {
                "type": "ORCID"
              }
            }
          ],
          "affiliation": [
            "State University of the Tocantina Region of Maranhão, Center for Exact, Natural and Technological Sciences, Imperatriz, MA, Brazil."
          ]
        }
      ]
    }
  ],
  "authorIdList": [
    {
      "authorId": [
        {
          "_": "0000-0002-8089-730X",
          "$": {
            "type": "ORCID"
          }
        }
      ]
    }
  ],
  "journalInfo": [
    {
      "volume": [
        "2018"
      ],
      "journalIssueId": [
        "2654636"
      ],
      "dateOfPublication": [
        "2018 "
      ],
      "monthOfPublication": [
        "0"
      ],
      "yearOfPublication": [
        "2018"
      ],
      "printPublicationDate": [
        "2018-01-01"
      ],
      "journal": [
        {
          "title": [
            "TheScientificWorldJournal"
          ],
          "ISOAbbreviation": [
            "ScientificWorldJournal"
          ],
          "medlineAbbreviation": [
            "ScientificWorldJournal"
          ],
          "NLMid": [
            "101131163"
          ],
          "ISSN": [
            "2356-6140"
          ],
          "ESSN": [
            "1537-744X"
          ]
        }
      ]
    }
  ],
  "pubYear": [
    "2018"
  ],
  "pageInfo": [
    "7405736"
  ],
  "abstractText": [
    "To assess the activities of essential oils derived from the trunk bark of Cinnamomum zeylanicum (EOCz) and Cinnamomum cassia (EOCc) as well as cinnamaldehyde on bacterial biofilms of clinical interest. Antimicrobial activity was assessed by the broth microdilution method to determine minimum inhibitory concentrations (MICs). Antibiofilm activity was assessed by quantifying the biomass and determining the number of viable cells. The chemical composition of the essential oils was determined. The results showed that the major component of EOCz and EOCc was cinnamaldehyde. For the assayed substances, biofilm biomasses were reduced by up to 99.9%, and Streptococcus pyogenes, Pseudomonas aeruginosa, and Escherichia coli biofilms were sensitive to all of the concentrations and substances analysed. In cell viability tests, 2 mg/ml of cinnamaldehyde reduced the number of viable cells by 5.74 Log CFU/ml. EOCz, EOCc, and cinnamaldehyde exhibited antimicrobial and antibiofilm activities. This work describes substances with potential use against infections caused by bacterial biofilms."
  ],
  "affiliation": [
    "University Center UNINTA, Exact Sciences Center, Sobral, CE, Brazil."
  ],
  "language": [
    "eng"
  ],
  "pubModel": [
    "Electronic-eCollection"
  ],
  "pubTypeList": [
    {
      "pubType": [
        "research-article",
        "Journal Article"
      ]
    }
  ],
  "meshHeadingList": [
    {
      "meshHeading": [
        {
          "majorTopic_YN": [
            "N"
          ],
          "descriptorName": [
            "Biofilms"
          ],
          "meshQualifierList": [
            {
              "meshQualifier": [
                {
                  "abbreviation": [
                    "DE"
                  ],
                  "qualifierName": [
                    "drug effects"
                  ],
                  "majorTopic_YN": [
                    "Y"
                  ]
                }
              ]
            }
          ]
        },
        {
          "majorTopic_YN": [
            "N"
          ],
          "descriptorName": [
            "Pseudomonas aeruginosa"
          ],
          "meshQualifierList": [
            {
              "meshQualifier": [
                {
                  "abbreviation": [
                    "DE"
                  ],
                  "qualifierName": [
                    "drug effects"
                  ],
                  "majorTopic_YN": [
                    "N"
                  ]
                }
              ]
            }
          ]
        },
        {
          "majorTopic_YN": [
            "N"
          ],
          "descriptorName": [
            "Escherichia coli"
          ],
          "meshQualifierList": [
            {
              "meshQualifier": [
                {
                  "abbreviation": [
                    "DE"
                  ],
                  "qualifierName": [
                    "drug effects"
                  ],
                  "majorTopic_YN": [
                    "N"
                  ]
                }
              ]
            }
          ]
        },
        {
          "majorTopic_YN": [
            "N"
          ],
          "descriptorName": [
            "Streptococcus pyogenes"
          ],
          "meshQualifierList": [
            {
              "meshQualifier": [
                {
                  "abbreviation": [
                    "DE"
                  ],
                  "qualifierName": [
                    "drug effects"
                  ],
                  "majorTopic_YN": [
                    "N"
                  ]
                }
              ]
            }
          ]
        },
        {
          "majorTopic_YN": [
            "N"
          ],
          "descriptorName": [
            "Cinnamomum"
          ],
          "meshQualifierList": [
            {
              "meshQualifier": [
                {
                  "abbreviation": [
                    "DE"
                  ],
                  "qualifierName": [
                    "drug effects"
                  ],
                  "majorTopic_YN": [
                    "Y"
                  ]
                }
              ]
            }
          ]
        },
        {
          "majorTopic_YN": [
            "N"
          ],
          "descriptorName": [
            "Oils, Volatile"
          ]
        },
        {
          "majorTopic_YN": [
            "N"
          ],
          "descriptorName": [
            "Plant Oils"
          ],
          "meshQualifierList": [
            {
              "meshQualifier": [
                {
                  "abbreviation": [
                    "PD"
                  ],
                  "qualifierName": [
                    "pharmacology"
                  ],
                  "majorTopic_YN": [
                    "Y"
                  ]
                }
              ]
            }
          ]
        },
        {
          "majorTopic_YN": [
            "N"
          ],
          "descriptorName": [
            "Anti-Bacterial Agents"
          ],
          "meshQualifierList": [
            {
              "meshQualifier": [
                {
                  "abbreviation": [
                    "PD"
                  ],
                  "qualifierName": [
                    "pharmacology"
                  ],
                  "majorTopic_YN": [
                    "Y"
                  ]
                }
              ]
            }
          ]
        },
        {
          "majorTopic_YN": [
            "N"
          ],
          "descriptorName": [
            "Microbial Sensitivity Tests"
          ]
        }
      ]
    }
  ],
  "chemicalList": [
    {
      "chemical": [
        {
          "name": [
            "Anti-Bacterial Agents"
          ],
          "registryNumber": [
            "0"
          ]
        },
        {
          "name": [
            "Oils, Volatile"
          ],
          "registryNumber": [
            "0"
          ]
        },
        {
          "name": [
            "Plant Oils"
          ],
          "registryNumber": [
            "0"
          ]
        }
      ]
    }
  ],
  "subsetList": [
    {
      "subset": [
        {
          "code": [
            "IM"
          ],
          "name": [
            "Index Medicus"
          ]
        }
      ]
    }
  ],
  "fullTextUrlList": [
    {
      "fullTextUrl": [
        {
          "availability": [
            "Open access"
          ],
          "availabilityCode": [
            "OA"
          ],
          "documentStyle": [
            "pdf"
          ],
          "site": [
            "Europe_PMC"
          ],
          "url": [
            "http://europepmc.org/articles/PMC6011056?pdf=render"
          ]
        },
        {
          "availability": [
            "Open access"
          ],
          "availabilityCode": [
            "OA"
          ],
          "documentStyle": [
            "html"
          ],
          "site": [
            "Europe_PMC"
          ],
          "url": [
            "http://europepmc.org/articles/PMC6011056"
          ]
        },
        {
          "availability": [
            "Subscription required"
          ],
          "availabilityCode": [
            "S"
          ],
          "documentStyle": [
            "doi"
          ],
          "site": [
            "DOI"
          ],
          "url": [
            "https://doi.org/10.1155/2018/7405736"
          ]
        }
      ]
    }
  ],
  "isOpenAccess": [
    "Y"
  ],
  "inEPMC": [
    "Y"
  ],
  "inPMC": [
    "N"
  ],
  "hasPDF": [
    "Y"
  ],
  "hasBook": [
    "N"
  ],
  "hasSuppl": [
    "N"
  ],
  "citedByCount": [
    "1"
  ],
  "hasReferences": [
    "Y"
  ],
  "hasTextMinedTerms": [
    "Y"
  ],
  "hasDbCrossReferences": [
    "N"
  ],
  "hasLabsLinks": [
    "Y"
  ],
  "license": [
    "cc by"
  ],
  "authMan": [
    "N"
  ],
  "epmcAuthMan": [
    "N"
  ],
  "nihAuthMan": [
    "N"
  ],
  "hasTMAccessionNumbers": [
    "N"
  ],
  "dateOfCompletion": [
    "2018-11-05"
  ],
  "dateOfCreation": [
    "2018-07-07"
  ],
  "firstIndexDate": [
    "2018-07-07"
  ],
  "dateOfRevision": [
    "2018-11-05"
  ],
  "electronicPublicationDate": [
    "2018-06-06"
  ],
  "firstPublicationDate": [
    "2018-06-06"
  ]
}